<tv channelGridKey="68b9f5a3d60e5dd29263c7ac">
<MediaContainer offset="0" totalSize="26" identifier="tv.plex.provider.epg" size="26"><Video guid="plex://episode/695d020b524beaf54d9052f0" key="/library/metadata/695d020b524beaf54d9052f0" ratingKey="695d020b524beaf54d9052f0" summary="Enjoy peanut candy, steamed tteok, honey citron rice snacks, and a refreshing bowl of Korean bingsu." type="episode" contentRating="TV-G" duration="3270000" grandparentArt="https://provider-static.plex.tv/epg/cms/production/aef863b1-8d06-4754-a177-3b0c2f19bfde/NEW_KFOOD_Horizontal_Default_Artwork.jpg" grandparentGuid="plex://show/68b9f5a7486bf118339b1c02" grandparentKey="/library/metadata/68b9f5a7486bf118339b1c02" grandparentRatingKey="68b9f5a7486bf118339b1c02" grandparentThumb="https://provider-static.plex.tv/epg/cms/production/62528d3f-fc1e-4168-bbb1-ee9b08230eb5/NEW_KFOOD_Vertical_Default_Artwork.jpg" grandparentTitle="Food Kingdom" grandparentType="show" index="15" originallyAvailableAt="2024-10-16T09:54:15.816Z" parentIndex="1" requiresConsent="1" skipParent="1" thumb="https://ingest-assets.wurl.com/430064/158931713-0.jpeg" title="Food Kingdom: Korean Rice Cakes and Snacks" userState="0" year="2024"><Image alt="Food Kingdom: Korean Rice Cakes and Snacks" type="coverArt" url="https://provider-static.plex.tv/epg/cms/production/aef863b1-8d06-4754-a177-3b0c2f19bfde/NEW_KFOOD_Horizontal_Default_Artwork.jpg"/><Image alt="Food Kingdom: Korean Rice Cakes and Snacks" type="coverPoster" url="https://provider-static.plex.tv/epg/cms/production/62528d3f-fc1e-4168-bbb1-ee9b08230eb5/NEW_KFOOD_Vertical_Default_Artwork.jpg"/><Image alt="Food Kingdom: Korean Rice Cakes and Snacks" type="snapshot" url="https://ingest-assets.wurl.com/430064/158931713-0.jpeg"/><Genre filter="genre=6529021f0f3f142ea6049ecf" id="6529021f0f3f142ea6049ecf" key="/library/sections/home/all?genre=6529021f0f3f142ea6049ecf" ratingKey="genre_6529021f0f3f142ea6049ecf" slug="international" tag="International" type="directory" context="tag.genre"/><Media beginsAt="1777926658" duration="3270000" endsAt="1777929928" id="69f3f4fcf84cf881d6b4987b" onAir="0" premiere="0" videoResolution="720" origin="livetv"/></Video><Video guid="plex://episode/695d020c524beaf54d9052f4" key="/library/metadata/695d020c524beaf54d9052f4" ratingKey="695d020c524beaf54d9052f4" summary="Enjoy long-sized pizzas, bulgogi gorgonzola, and creamy pasta dishes, plus Korea’s biggest burger." type="episode" contentRating="TV-G" duration="3078000" grandparentArt="https://provider-static.plex.tv/epg/cms/production/aef863b1-8d06-4754-a177-3b0c2f19bfde/NEW_KFOOD_Horizontal_Default_Artwork.jpg" grandparentGuid="plex://show/68b9f5a7486bf118339b1c02" grandparentKey="/library/metadata/68b9f5a7486bf118339b1c02" grandparentRatingKey="68b9f5a7486bf118339b1c02" grandparentThumb="https://provider-static.plex.tv/epg/cms/production/62528d3f-fc1e-4168-bbb1-ee9b08230eb5/NEW_KFOOD_Vertical_Default_Artwork.jpg" grandparentTitle="Food Kingdom" grandparentType="show" index="11" originallyAvailableAt="2024-10-16T09:54:15.814Z" parentIndex="1" requiresConsent="1" skipParent="1" thumb="https://ingest-assets.wurl.com/430064/158931709-0.jpeg" title="Food Kingdom: Pizza and Pasta Delights" userState="0" year="2024"><Image alt="Food Kingdom: Pizza and Pasta Delights" type="coverArt" url="https://provider-static.plex.tv/epg/cms/production/aef863b1-8d06-4754-a177-3b0c2f19bfde/NEW_KFOOD_Horizontal_Default_Artwork.jpg"/><Image alt="Food Kingdom: Pizza and Pasta Delights" type="coverPoster" url="https://provider-static.plex.tv/epg/cms/production/62528d3f-fc1e-4168-bbb1-ee9b08230eb5/NEW_KFOOD_Vertical_Default_Artwork.jpg"/><Image alt="Food Kingdom: Pizza and Pasta Delights" type="snapshot" url="https://ingest-assets.wurl.com/430064/158931709-0.jpeg"/><Genre filter="genre=6529021f0f3f142ea6049ecf" id="6529021f0f3f142ea6049ecf" key="/library/sections/home/all?genre=6529021f0f3f142ea6049ecf" ratingKey="genre_6529021f0f3f142ea6049ecf" slug="international" tag="International" type="directory" context="tag.genre"/><Media beginsAt="1777902107" duration="3078000" endsAt="1777905185" id="69f3f4fcf84cf881d6b49873" onAir="0" premiere="0" videoResolution="720" origin="livetv"/></Video><Video guid="plex://episode/698731c8b1d98611ba5ec524" key="/library/metadata/698731c8b1d98611ba5ec524" ratingKey="698731c8b1d98611ba5ec524" summary="Indulge in intense red tteokbokki, five-flavored sundae, and a selection of Jeju-style Korean snacks." type="episode" contentRating="TV-G" duration="3617000" grandparentArt="https://provider-static.plex.tv/epg/cms/production/aef863b1-8d06-4754-a177-3b0c2f19bfde/NEW_KFOOD_Horizontal_Default_Artwork.jpg" grandparentGuid="plex://show/68b9f5a7486bf118339b1c02" grandparentKey="/library/metadata/68b9f5a7486bf118339b1c02" grandparentRatingKey="68b9f5a7486bf118339b1c02" grandparentThumb="https://provider-static.plex.tv/epg/cms/production/62528d3f-fc1e-4168-bbb1-ee9b08230eb5/NEW_KFOOD_Vertical_Default_Artwork.jpg" grandparentTitle="Food Kingdom" grandparentType="show" index="26" originallyAvailableAt="2024-11-05T04:42:57.437Z" parentIndex="1" requiresConsent="1" skipParent="1" thumb="https://ingest-assets.wurl.com/430279/160802902-0.jpeg" title="Food Kingdom: Tteokbokki and Sundae Special" userState="0" year="2024"><Image alt="Food Kingdom: Tteokbokki and Sundae Special" type="coverArt" url="https://provider-static.plex.tv/epg/cms/production/aef863b1-8d06-4754-a177-3b0c2f19bfde/NEW_KFOOD_Horizontal_Default_Artwork.jpg"/><Image alt="Food Kingdom: Tteokbokki and Sundae Special" type="coverPoster" url="https://provider-static.plex.tv/epg/cms/production/62528d3f-fc1e-4168-bbb1-ee9b08230eb5/NEW_KFOOD_Vertical_Default_Artwork.jpg"/><Image alt="Food Kingdom: Tteokbokki and Sundae Special" type="snapshot" url="https://ingest-assets.wurl.com/430279/160802902-0.jpeg"/><Genre filter="genre=6529021f0f3f142ea6049ecf" id="6529021f0f3f142ea6049ecf" key="/library/sections/home/all?genre=6529021f0f3f142ea6049ecf" ratingKey="genre_6529021f0f3f142ea6049ecf" slug="international" tag="International" type="directory" context="tag.genre"/><Media beginsAt="1777905185" duration="3617000" endsAt="1777908802" id="69f3f4fcf84cf881d6b49874" onAir="0" premiere="0" videoResolution="720" origin="livetv"/></Video><Video guid="plex://episode/69a18f7ac072f55592614b17" key="/library/metadata/69a18f7ac072f55592614b17" ratingKey="69a18f7ac072f55592614b17" summary="Enjoy a delicious snack combo of tteokbokki, gimbap, and fishcake from Korea’s famous eateries and markets." type="episode" contentRating="TV-G" duration="3600000" grandparentArt="https://provider-static.plex.tv/epg/cms/production/aef863b1-8d06-4754-a177-3b0c2f19bfde/NEW_KFOOD_Horizontal_Default_Artwork.jpg" grandparentGuid="plex://show/68b9f5a7486bf118339b1c02" grandparentKey="/library/metadata/68b9f5a7486bf118339b1c02" grandparentRatingKey="68b9f5a7486bf118339b1c02" grandparentThumb="https://provider-static.plex.tv/epg/cms/production/62528d3f-fc1e-4168-bbb1-ee9b08230eb5/NEW_KFOOD_Vertical_Default_Artwork.jpg" grandparentTitle="Food Kingdom" grandparentType="show" index="19" originallyAvailableAt="2024-10-16T09:54:15.818Z" parentIndex="1" requiresConsent="1" skipParent="1" thumb="https://ingest-assets.wurl.com/430064/158931717-0.jpeg" title="Food Kingdom: Korean Snack Combo" userState="0" year="2024"><Image alt="Food Kingdom: Korean Snack Combo" type="coverArt" url="https://provider-static.plex.tv/epg/cms/production/aef863b1-8d06-4754-a177-3b0c2f19bfde/NEW_KFOOD_Horizontal_Default_Artwork.jpg"/><Image alt="Food Kingdom: Korean Snack Combo" type="coverPoster" url="https://provider-static.plex.tv/epg/cms/production/62528d3f-fc1e-4168-bbb1-ee9b08230eb5/NEW_KFOOD_Vertical_Default_Artwork.jpg"/><Image alt="Food Kingdom: Korean Snack Combo" type="snapshot" url="https://ingest-assets.wurl.com/430064/158931717-0.jpeg"/><Genre filter="genre=6529021f0f3f142ea6049ecf" id="6529021f0f3f142ea6049ecf" key="/library/sections/home/all?genre=6529021f0f3f142ea6049ecf" ratingKey="genre_6529021f0f3f142ea6049ecf" slug="international" tag="International" type="directory" context="tag.genre"/><Media beginsAt="1777932849" duration="3600000" endsAt="1777936449" id="69f3f4fcf84cf881d6b4987d" onAir="0" premiere="0" videoResolution="720" origin="livetv"/></Video><Video guid="plex://episode/69c91cb4e016f101742b8b07" key="/library/metadata/69c91cb4e016f101742b8b07" ratingKey="69c91cb4e016f101742b8b07" summary="Delight in grilled seafood, squid green onion jeon, and seafood kalguksu for a seafood feast." type="episode" contentRating="TV-G" duration="3118000" grandparentArt="https://provider-static.plex.tv/epg/cms/production/aef863b1-8d06-4754-a177-3b0c2f19bfde/NEW_KFOOD_Horizontal_Default_Artwork.jpg" grandparentGuid="plex://show/68b9f5a7486bf118339b1c02" grandparentKey="/library/metadata/68b9f5a7486bf118339b1c02" grandparentRatingKey="68b9f5a7486bf118339b1c02" grandparentThumb="https://provider-static.plex.tv/epg/cms/production/62528d3f-fc1e-4168-bbb1-ee9b08230eb5/NEW_KFOOD_Vertical_Default_Artwork.jpg" grandparentTitle="Food Kingdom" grandparentType="show" index="13" originallyAvailableAt="2024-10-16T09:54:15.815Z" parentIndex="1" requiresConsent="1" skipParent="1" thumb="https://ingest-assets.wurl.com/430064/158931711-0.jpeg" title="Food Kingdom: Seafood Grill and Korean Jeon" userState="0" year="2024"><Image alt="Food Kingdom: Seafood Grill and Korean Jeon" type="coverArt" url="https://provider-static.plex.tv/epg/cms/production/aef863b1-8d06-4754-a177-3b0c2f19bfde/NEW_KFOOD_Horizontal_Default_Artwork.jpg"/><Image alt="Food Kingdom: Seafood Grill and Korean Jeon" type="coverPoster" url="https://provider-static.plex.tv/epg/cms/production/62528d3f-fc1e-4168-bbb1-ee9b08230eb5/NEW_KFOOD_Vertical_Default_Artwork.jpg"/><Image alt="Food Kingdom: Seafood Grill and Korean Jeon" type="snapshot" url="https://ingest-assets.wurl.com/430064/158931711-0.jpeg"/><Genre filter="genre=6529021f0f3f142ea6049ecf" id="6529021f0f3f142ea6049ecf" key="/library/sections/home/all?genre=6529021f0f3f142ea6049ecf" ratingKey="genre_6529021f0f3f142ea6049ecf" slug="international" tag="International" type="directory" context="tag.genre"/><Media beginsAt="1777917853" duration="3118000" endsAt="1777920971" id="69f3f4fcf84cf881d6b49878" onAir="1" premiere="0" videoResolution="720" origin="livetv"/></Video><Video guid="plex://episode/69c91cb5e016f101742b8b0d" key="/library/metadata/69c91cb5e016f101742b8b0d" ratingKey="69c91cb5e016f101742b8b0d" summary="Indulge in soft castella, dalgona scones, and Czech trdelník for a delicious variety of sweet treats." type="episode" contentRating="TV-G" duration="2921000" grandparentArt="https://provider-static.plex.tv/epg/cms/production/aef863b1-8d06-4754-a177-3b0c2f19bfde/NEW_KFOOD_Horizontal_Default_Artwork.jpg" grandparentGuid="plex://show/68b9f5a7486bf118339b1c02" grandparentKey="/library/metadata/68b9f5a7486bf118339b1c02" grandparentRatingKey="68b9f5a7486bf118339b1c02" grandparentThumb="https://provider-static.plex.tv/epg/cms/production/62528d3f-fc1e-4168-bbb1-ee9b08230eb5/NEW_KFOOD_Vertical_Default_Artwork.jpg" grandparentTitle="Food Kingdom" grandparentType="show" index="12" originallyAvailableAt="2024-10-16T09:54:15.815Z" parentIndex="1" requiresConsent="1" skipParent="1" thumb="https://ingest-assets.wurl.com/430064/158931710-0.jpeg" title="Food Kingdom: Castella and Sweet Creations" userState="0" year="2024"><Image alt="Food Kingdom: Castella and Sweet Creations" type="coverArt" url="https://provider-static.plex.tv/epg/cms/production/aef863b1-8d06-4754-a177-3b0c2f19bfde/NEW_KFOOD_Horizontal_Default_Artwork.jpg"/><Image alt="Food Kingdom: Castella and Sweet Creations" type="coverPoster" url="https://provider-static.plex.tv/epg/cms/production/62528d3f-fc1e-4168-bbb1-ee9b08230eb5/NEW_KFOOD_Vertical_Default_Artwork.jpg"/><Image alt="Food Kingdom: Castella and Sweet Creations" type="snapshot" url="https://ingest-assets.wurl.com/430064/158931710-0.jpeg"/><Genre filter="genre=6529021f0f3f142ea6049ecf" id="6529021f0f3f142ea6049ecf" key="/library/sections/home/all?genre=6529021f0f3f142ea6049ecf" ratingKey="genre_6529021f0f3f142ea6049ecf" slug="international" tag="International" type="directory" context="tag.genre"/><Media beginsAt="1777929928" duration="2921000" endsAt="1777932849" id="69f3f4fcf84cf881d6b4987c" onAir="0" premiere="0" videoResolution="720" origin="livetv"/></Video><Video guid="plex://episode/69e423f34f1b45e92d70621b" key="/library/metadata/69e423f34f1b45e92d70621b" ratingKey="69e423f34f1b45e92d70621b" summary="Enjoy shrimp dumplings, giant drum-baked dumplings, and Korean street bread for a savory and satisfying combo." type="episode" contentRating="TV-G" duration="2716000" grandparentArt="https://provider-static.plex.tv/epg/cms/production/aef863b1-8d06-4754-a177-3b0c2f19bfde/NEW_KFOOD_Horizontal_Default_Artwork.jpg" grandparentGuid="plex://show/68b9f5a7486bf118339b1c02" grandparentKey="/library/metadata/68b9f5a7486bf118339b1c02" grandparentRatingKey="68b9f5a7486bf118339b1c02" grandparentThumb="https://provider-static.plex.tv/epg/cms/production/62528d3f-fc1e-4168-bbb1-ee9b08230eb5/NEW_KFOOD_Vertical_Default_Artwork.jpg" grandparentTitle="Food Kingdom" grandparentType="show" index="30" originallyAvailableAt="2024-11-05T04:42:57.435Z" parentIndex="1" requiresConsent="1" skipParent="1" thumb="https://ingest-assets.wurl.com/430279/160802898-0.jpeg" title="Food Kingdom: Dumplings and Korean Street Breads" userState="0" year="2024"><Image alt="Food Kingdom: Dumplings and Korean Street Breads" type="coverArt" url="https://provider-static.plex.tv/epg/cms/production/aef863b1-8d06-4754-a177-3b0c2f19bfde/NEW_KFOOD_Horizontal_Default_Artwork.jpg"/><Image alt="Food Kingdom: Dumplings and Korean Street Breads" type="coverPoster" url="https://provider-static.plex.tv/epg/cms/production/62528d3f-fc1e-4168-bbb1-ee9b08230eb5/NEW_KFOOD_Vertical_Default_Artwork.jpg"/><Image alt="Food Kingdom: Dumplings and Korean Street Breads" type="snapshot" url="https://ingest-assets.wurl.com/430279/160802898-0.jpeg"/><Genre filter="genre=6529021f0f3f142ea6049ecf" id="6529021f0f3f142ea6049ecf" key="/library/sections/home/all?genre=6529021f0f3f142ea6049ecf" ratingKey="genre_6529021f0f3f142ea6049ecf" slug="international" tag="International" type="directory" context="tag.genre"/><Media beginsAt="1777908802" duration="2716000" endsAt="1777911518" id="69f3f4fcf84cf881d6b49875" onAir="0" premiere="0" videoResolution="720" origin="livetv"/></Video><Video guid="plex://episode/69e8c154577d2a3bcdbdedd7" key="/library/metadata/69e8c154577d2a3bcdbdedd7" ratingKey="69e8c154577d2a3bcdbdedd7" summary="Taste flower crepes, frozen Dubai tarts, and crispy rice chocolate for a colorful fusion dessert experience." type="episode" contentRating="TV-G" duration="3087000" grandparentArt="https://provider-static.plex.tv/epg/cms/production/aef863b1-8d06-4754-a177-3b0c2f19bfde/NEW_KFOOD_Horizontal_Default_Artwork.jpg" grandparentGuid="plex://show/68b9f5a7486bf118339b1c02" grandparentKey="/library/metadata/68b9f5a7486bf118339b1c02" grandparentRatingKey="68b9f5a7486bf118339b1c02" grandparentThumb="https://provider-static.plex.tv/epg/cms/production/62528d3f-fc1e-4168-bbb1-ee9b08230eb5/NEW_KFOOD_Vertical_Default_Artwork.jpg" grandparentTitle="Food Kingdom" grandparentType="show" index="28" originallyAvailableAt="2024-11-05T04:42:57.436Z" parentIndex="1" requiresConsent="1" skipParent="1" thumb="https://ingest-assets.wurl.com/430279/160802900-0.jpeg" title="Food Kingdom: Fusion Desserts" userState="0" year="2024"><Image alt="Food Kingdom: Fusion Desserts" type="coverArt" url="https://provider-static.plex.tv/epg/cms/production/aef863b1-8d06-4754-a177-3b0c2f19bfde/NEW_KFOOD_Horizontal_Default_Artwork.jpg"/><Image alt="Food Kingdom: Fusion Desserts" type="coverPoster" url="https://provider-static.plex.tv/epg/cms/production/62528d3f-fc1e-4168-bbb1-ee9b08230eb5/NEW_KFOOD_Vertical_Default_Artwork.jpg"/><Image alt="Food Kingdom: Fusion Desserts" type="snapshot" url="https://ingest-assets.wurl.com/430279/160802900-0.jpeg"/><Genre filter="genre=6529021f0f3f142ea6049ecf" id="6529021f0f3f142ea6049ecf" key="/library/sections/home/all?genre=6529021f0f3f142ea6049ecf" ratingKey="genre_6529021f0f3f142ea6049ecf" slug="international" tag="International" type="directory" context="tag.genre"/><Media beginsAt="1777863346" duration="3087000" endsAt="1777866433" id="69f3f4fcf84cf881d6b49868" onAir="0" premiere="0" videoResolution="720" origin="livetv"/></Video><Video guid="plex://episode/69f3f4f5f84cf881d6b497f3" key="/library/metadata/69f3f4f5f84cf881d6b497f3" ratingKey="69f3f4f5f84cf881d6b497f3" summary="Indulge in a world of pizza delights from classic choices to unique creations." type="episode" contentRating="TV-G" duration="4151000" grandparentArt="https://dki01q1l7yn3y.cloudfront.net/thumbnails-platform-prod/assets/cs::content::shows/6838-8886/14005672-default_v5.png" grandparentGuid="plex://show/68febcb7addba09ea3db056d" grandparentKey="/library/metadata/68febcb7addba09ea3db056d" grandparentRatingKey="68febcb7addba09ea3db056d" grandparentThumb="https://provider-static.plex.tv/epg/cms/production/62528d3f-fc1e-4168-bbb1-ee9b08230eb5/NEW_KFOOD_Vertical_Default_Artwork.jpg" grandparentTitle="FoodieBoy" grandparentType="show" index="8" originallyAvailableAt="2023-12-06T00:55:28.866Z" parentIndex="1" requiresConsent="1" skipParent="1" thumb="https://ingest-assets.wurl.com/426834/133697840-0.jpeg" title="FoodieBoy : Amazing Special Pizza" userState="0" year="2023"><Image alt="FoodieBoy : Amazing Special Pizza" type="coverArt" url="https://dki01q1l7yn3y.cloudfront.net/thumbnails-platform-prod/assets/cs::content::shows/6838-8886/14005672-default_v5.png"/><Image alt="FoodieBoy : Amazing Special Pizza" type="coverPoster" url="https://provider-static.plex.tv/epg/cms/production/62528d3f-fc1e-4168-bbb1-ee9b08230eb5/NEW_KFOOD_Vertical_Default_Artwork.jpg"/><Image alt="FoodieBoy : Amazing Special Pizza" type="snapshot" url="https://ingest-assets.wurl.com/426834/133697840-0.jpeg"/><Genre filter="genre=6529021f0f3f142ea6049ecf" id="6529021f0f3f142ea6049ecf" key="/library/sections/home/all?genre=6529021f0f3f142ea6049ecf" ratingKey="genre_6529021f0f3f142ea6049ecf" slug="international" tag="International" type="directory" context="tag.genre"/><Media beginsAt="1777852384" duration="4150000" endsAt="1777856534" id="69f3f4fcf84cf881d6b49865" onAir="0" premiere="0" videoResolution="720" origin="livetv"/></Video><Video guid="plex://episode/69f3f4f5f84cf881d6b497f4" key="/library/metadata/69f3f4f5f84cf881d6b497f4" ratingKey="69f3f4f5f84cf881d6b497f4" summary="Experience the nostalgia of Korean school food classics including iconic dishes and beloved street food." type="episode" contentRating="TV-G" duration="3849000" grandparentArt="https://dki01q1l7yn3y.cloudfront.net/thumbnails-platform-prod/assets/cs::content::shows/6838-8886/14005672-default_v5.png" grandparentGuid="plex://show/68febcb7addba09ea3db056d" grandparentKey="/library/metadata/68febcb7addba09ea3db056d" grandparentRatingKey="68febcb7addba09ea3db056d" grandparentThumb="https://provider-static.plex.tv/epg/cms/production/62528d3f-fc1e-4168-bbb1-ee9b08230eb5/NEW_KFOOD_Vertical_Default_Artwork.jpg" grandparentTitle="FoodieBoy" grandparentType="show" index="4" originallyAvailableAt="2023-12-06T00:55:45.436Z" parentIndex="2" requiresConsent="1" skipParent="1" thumb="https://ingest-assets.wurl.com/426833/133697815-0.jpeg" title="FoodieBoy : Korean School Food" userState="0" year="2023"><Image alt="FoodieBoy : Korean School Food" type="coverArt" url="https://dki01q1l7yn3y.cloudfront.net/thumbnails-platform-prod/assets/cs::content::shows/6838-8886/14005672-default_v5.png"/><Image alt="FoodieBoy : Korean School Food" type="coverPoster" url="https://provider-static.plex.tv/epg/cms/production/62528d3f-fc1e-4168-bbb1-ee9b08230eb5/NEW_KFOOD_Vertical_Default_Artwork.jpg"/><Image alt="FoodieBoy : Korean School Food" type="snapshot" url="https://ingest-assets.wurl.com/426833/133697815-0.jpeg"/><Genre filter="genre=6529021f0f3f142ea6049ecf" id="6529021f0f3f142ea6049ecf" key="/library/sections/home/all?genre=6529021f0f3f142ea6049ecf" ratingKey="genre_6529021f0f3f142ea6049ecf" slug="international" tag="International" type="directory" context="tag.genre"/><Media beginsAt="1777866433" duration="3849000" endsAt="1777870282" id="69f3f4fcf84cf881d6b49869" onAir="0" premiere="0" videoResolution="720" origin="livetv"/></Video><Video guid="plex://episode/69f3f4f5f84cf881d6b497f5" key="/library/metadata/69f3f4f5f84cf881d6b497f5" ratingKey="69f3f4f5f84cf881d6b497f5" summary="Immerse in a world of sweet delights with a perfect blend of textures and flavors." type="episode" contentRating="TV-G" duration="3223000" grandparentArt="https://dki01q1l7yn3y.cloudfront.net/thumbnails-platform-prod/assets/cs::content::shows/6838-8886/14005672-default_v5.png" grandparentGuid="plex://show/68febcb7addba09ea3db056d" grandparentKey="/library/metadata/68febcb7addba09ea3db056d" grandparentRatingKey="68febcb7addba09ea3db056d" grandparentThumb="https://provider-static.plex.tv/epg/cms/production/62528d3f-fc1e-4168-bbb1-ee9b08230eb5/NEW_KFOOD_Vertical_Default_Artwork.jpg" grandparentTitle="FoodieBoy" grandparentType="show" index="18" originallyAvailableAt="2023-12-06T00:55:45.455Z" parentIndex="2" requiresConsent="1" skipParent="1" thumb="https://ingest-assets.wurl.com/426833/133697829-0.jpeg" title="FoodieBoy : Breads and Waffles in Korea" userState="0" year="2023"><Image alt="FoodieBoy : Breads and Waffles in Korea" type="coverArt" url="https://dki01q1l7yn3y.cloudfront.net/thumbnails-platform-prod/assets/cs::content::shows/6838-8886/14005672-default_v5.png"/><Image alt="FoodieBoy : Breads and Waffles in Korea" type="coverPoster" url="https://provider-static.plex.tv/epg/cms/production/62528d3f-fc1e-4168-bbb1-ee9b08230eb5/NEW_KFOOD_Vertical_Default_Artwork.jpg"/><Image alt="FoodieBoy : Breads and Waffles in Korea" type="snapshot" url="https://ingest-assets.wurl.com/426833/133697829-0.jpeg"/><Genre filter="genre=6529021f0f3f142ea6049ecf" id="6529021f0f3f142ea6049ecf" key="/library/sections/home/all?genre=6529021f0f3f142ea6049ecf" ratingKey="genre_6529021f0f3f142ea6049ecf" slug="international" tag="International" type="directory" context="tag.genre"/><Media beginsAt="1777873557" duration="3223000" endsAt="1777876780" id="69f3f4fcf84cf881d6b4986b" onAir="0" premiere="0" videoResolution="720" origin="livetv"/></Video><Video guid="plex://episode/69f3f4f5f84cf881d6b497f6" key="/library/metadata/69f3f4f5f84cf881d6b497f6" ratingKey="69f3f4f5f84cf881d6b497f6" summary="Elevate your burger experience with an impressive selection of handcrafted options." type="episode" contentRating="TV-G" duration="3830000" grandparentArt="https://dki01q1l7yn3y.cloudfront.net/thumbnails-platform-prod/assets/cs::content::shows/6838-8886/14005672-default_v5.png" grandparentGuid="plex://show/68febcb7addba09ea3db056d" grandparentKey="/library/metadata/68febcb7addba09ea3db056d" grandparentRatingKey="68febcb7addba09ea3db056d" grandparentThumb="https://provider-static.plex.tv/epg/cms/production/62528d3f-fc1e-4168-bbb1-ee9b08230eb5/NEW_KFOOD_Vertical_Default_Artwork.jpg" grandparentTitle="FoodieBoy" grandparentType="show" index="3" originallyAvailableAt="2023-12-06T00:55:28.864Z" parentIndex="1" requiresConsent="1" skipParent="1" thumb="https://ingest-assets.wurl.com/426834/133697835-0.jpeg" title="FoodieBoy : Amazing Handmade Burger" userState="0" year="2023"><Image alt="FoodieBoy : Amazing Handmade Burger" type="coverArt" url="https://dki01q1l7yn3y.cloudfront.net/thumbnails-platform-prod/assets/cs::content::shows/6838-8886/14005672-default_v5.png"/><Image alt="FoodieBoy : Amazing Handmade Burger" type="coverPoster" url="https://provider-static.plex.tv/epg/cms/production/62528d3f-fc1e-4168-bbb1-ee9b08230eb5/NEW_KFOOD_Vertical_Default_Artwork.jpg"/><Image alt="FoodieBoy : Amazing Handmade Burger" type="snapshot" url="https://ingest-assets.wurl.com/426834/133697835-0.jpeg"/><Genre filter="genre=6529021f0f3f142ea6049ecf" id="6529021f0f3f142ea6049ecf" key="/library/sections/home/all?genre=6529021f0f3f142ea6049ecf" ratingKey="genre_6529021f0f3f142ea6049ecf" slug="international" tag="International" type="directory" context="tag.genre"/><Media beginsAt="1777883817" duration="3830000" endsAt="1777887647" id="69f3f4fcf84cf881d6b4986e" onAir="0" premiere="0" videoResolution="720" origin="livetv"/></Video><Video guid="plex://episode/69f3f4f5f84cf881d6b497f7" key="/library/metadata/69f3f4f5f84cf881d6b497f7" ratingKey="69f3f4f5f84cf881d6b497f7" summary="Satisfy your sweet tooth with an assortment of tantalizing fruit-inspired desserts." type="episode" contentRating="TV-G" duration="2734000" grandparentArt="https://dki01q1l7yn3y.cloudfront.net/thumbnails-platform-prod/assets/cs::content::shows/6838-8886/14005672-default_v5.png" grandparentGuid="plex://show/68febcb7addba09ea3db056d" grandparentKey="/library/metadata/68febcb7addba09ea3db056d" grandparentRatingKey="68febcb7addba09ea3db056d" grandparentThumb="https://provider-static.plex.tv/epg/cms/production/62528d3f-fc1e-4168-bbb1-ee9b08230eb5/NEW_KFOOD_Vertical_Default_Artwork.jpg" grandparentTitle="FoodieBoy" grandparentType="show" index="7" originallyAvailableAt="2023-12-06T00:55:28.865Z" parentIndex="1" requiresConsent="1" skipParent="1" thumb="https://ingest-assets.wurl.com/426834/133697839-0.jpeg" title="FoodieBoy : Amazing Fruit Dessert" userState="0" year="2023"><Image alt="FoodieBoy : Amazing Fruit Dessert" type="coverArt" url="https://dki01q1l7yn3y.cloudfront.net/thumbnails-platform-prod/assets/cs::content::shows/6838-8886/14005672-default_v5.png"/><Image alt="FoodieBoy : Amazing Fruit Dessert" type="coverPoster" url="https://provider-static.plex.tv/epg/cms/production/62528d3f-fc1e-4168-bbb1-ee9b08230eb5/NEW_KFOOD_Vertical_Default_Artwork.jpg"/><Image alt="FoodieBoy : Amazing Fruit Dessert" type="snapshot" url="https://ingest-assets.wurl.com/426834/133697839-0.jpeg"/><Genre filter="genre=6529021f0f3f142ea6049ecf" id="6529021f0f3f142ea6049ecf" key="/library/sections/home/all?genre=6529021f0f3f142ea6049ecf" ratingKey="genre_6529021f0f3f142ea6049ecf" slug="international" tag="International" type="directory" context="tag.genre"/><Media beginsAt="1777887647" duration="2734000" endsAt="1777890381" id="69f3f4fcf84cf881d6b4986f" onAir="0" premiere="0" videoResolution="720" origin="livetv"/></Video><Video guid="plex://episode/69f3f4f5f84cf881d6b497f8" key="/library/metadata/69f3f4f5f84cf881d6b497f8" ratingKey="69f3f4f5f84cf881d6b497f8" summary="Savor the rich and diverse flavors of Chinese cuisine in a world of taste." type="episode" contentRating="TV-G" duration="3605000" grandparentArt="https://dki01q1l7yn3y.cloudfront.net/thumbnails-platform-prod/assets/cs::content::shows/6838-8886/14005672-default_v5.png" grandparentGuid="plex://show/68febcb7addba09ea3db056d" grandparentKey="/library/metadata/68febcb7addba09ea3db056d" grandparentRatingKey="68febcb7addba09ea3db056d" grandparentThumb="https://provider-static.plex.tv/epg/cms/production/62528d3f-fc1e-4168-bbb1-ee9b08230eb5/NEW_KFOOD_Vertical_Default_Artwork.jpg" grandparentTitle="FoodieBoy" grandparentType="show" index="23" originallyAvailableAt="2023-12-06T00:55:28.870Z" parentIndex="1" requiresConsent="1" skipParent="1" thumb="https://ingest-assets.wurl.com/426834/133697855-0.jpeg" title="FoodieBoy : Chinese Food in Korea" userState="0" year="2023"><Image alt="FoodieBoy : Chinese Food in Korea" type="coverArt" url="https://dki01q1l7yn3y.cloudfront.net/thumbnails-platform-prod/assets/cs::content::shows/6838-8886/14005672-default_v5.png"/><Image alt="FoodieBoy : Chinese Food in Korea" type="coverPoster" url="https://provider-static.plex.tv/epg/cms/production/62528d3f-fc1e-4168-bbb1-ee9b08230eb5/NEW_KFOOD_Vertical_Default_Artwork.jpg"/><Image alt="FoodieBoy : Chinese Food in Korea" type="snapshot" url="https://ingest-assets.wurl.com/426834/133697855-0.jpeg"/><Genre filter="genre=6529021f0f3f142ea6049ecf" id="6529021f0f3f142ea6049ecf" key="/library/sections/home/all?genre=6529021f0f3f142ea6049ecf" ratingKey="genre_6529021f0f3f142ea6049ecf" slug="international" tag="International" type="directory" context="tag.genre"/><Media beginsAt="1777890381" duration="3605000" endsAt="1777893986" id="69f3f4fcf84cf881d6b49870" onAir="0" premiere="0" videoResolution="720" origin="livetv"/></Video><Video guid="plex://episode/69f3f4f6f84cf881d6b497f9" key="/library/metadata/69f3f4f6f84cf881d6b497f9" ratingKey="69f3f4f6f84cf881d6b497f9" summary="Enjoy a flavorful journey through a range of Korean chicken dishes." type="episode" contentRating="TV-G" duration="3267000" grandparentArt="https://dki01q1l7yn3y.cloudfront.net/thumbnails-platform-prod/assets/cs::content::shows/6838-8886/14005672-default_v5.png" grandparentGuid="plex://show/68febcb7addba09ea3db056d" grandparentKey="/library/metadata/68febcb7addba09ea3db056d" grandparentRatingKey="68febcb7addba09ea3db056d" grandparentThumb="https://provider-static.plex.tv/epg/cms/production/62528d3f-fc1e-4168-bbb1-ee9b08230eb5/NEW_KFOOD_Vertical_Default_Artwork.jpg" grandparentTitle="FoodieBoy" grandparentType="show" index="5" originallyAvailableAt="2023-12-06T00:55:28.865Z" parentIndex="1" requiresConsent="1" skipParent="1" thumb="https://ingest-assets.wurl.com/426834/133697837-0.jpeg" title="FoodieBoy : Korean Style Chicken" userState="0" year="2023"><Image alt="FoodieBoy : Korean Style Chicken" type="coverArt" url="https://dki01q1l7yn3y.cloudfront.net/thumbnails-platform-prod/assets/cs::content::shows/6838-8886/14005672-default_v5.png"/><Image alt="FoodieBoy : Korean Style Chicken" type="coverPoster" url="https://provider-static.plex.tv/epg/cms/production/62528d3f-fc1e-4168-bbb1-ee9b08230eb5/NEW_KFOOD_Vertical_Default_Artwork.jpg"/><Image alt="FoodieBoy : Korean Style Chicken" type="snapshot" url="https://ingest-assets.wurl.com/426834/133697837-0.jpeg"/><Genre filter="genre=6529021f0f3f142ea6049ecf" id="6529021f0f3f142ea6049ecf" key="/library/sections/home/all?genre=6529021f0f3f142ea6049ecf" ratingKey="genre_6529021f0f3f142ea6049ecf" slug="international" tag="International" type="directory" context="tag.genre"/><Media beginsAt="1777920971" duration="3267000" endsAt="1777924238" id="69f3f4fcf84cf881d6b49879" onAir="0" premiere="0" videoResolution="720" origin="livetv"/></Video><Video guid="plex://episode/69f3f4f6f84cf881d6b497fa" key="/library/metadata/69f3f4f6f84cf881d6b497fa" ratingKey="69f3f4f6f84cf881d6b497fa" summary="Unearth a world of unique and tantalizing cake creations sure to satisfy your sweet tooth." type="episode" contentRating="TV-G" duration="2420000" grandparentArt="https://dki01q1l7yn3y.cloudfront.net/thumbnails-platform-prod/assets/cs::content::shows/6838-8886/14005672-default_v5.png" grandparentGuid="plex://show/68febcb7addba09ea3db056d" grandparentKey="/library/metadata/68febcb7addba09ea3db056d" grandparentRatingKey="68febcb7addba09ea3db056d" grandparentThumb="https://provider-static.plex.tv/epg/cms/production/62528d3f-fc1e-4168-bbb1-ee9b08230eb5/NEW_KFOOD_Vertical_Default_Artwork.jpg" grandparentTitle="FoodieBoy" grandparentType="show" index="15" originallyAvailableAt="2023-12-06T00:55:28.868Z" parentIndex="1" requiresConsent="1" skipParent="1" thumb="https://ingest-assets.wurl.com/426834/133697847-0.jpeg" title="FoodieBoy : Amazing Special Cake" userState="0" year="2023"><Image alt="FoodieBoy : Amazing Special Cake" type="coverArt" url="https://dki01q1l7yn3y.cloudfront.net/thumbnails-platform-prod/assets/cs::content::shows/6838-8886/14005672-default_v5.png"/><Image alt="FoodieBoy : Amazing Special Cake" type="coverPoster" url="https://provider-static.plex.tv/epg/cms/production/62528d3f-fc1e-4168-bbb1-ee9b08230eb5/NEW_KFOOD_Vertical_Default_Artwork.jpg"/><Image alt="FoodieBoy : Amazing Special Cake" type="snapshot" url="https://ingest-assets.wurl.com/426834/133697847-0.jpeg"/><Genre filter="genre=6529021f0f3f142ea6049ecf" id="6529021f0f3f142ea6049ecf" key="/library/sections/home/all?genre=6529021f0f3f142ea6049ecf" ratingKey="genre_6529021f0f3f142ea6049ecf" slug="international" tag="International" type="directory" context="tag.genre"/><Media beginsAt="1777924238" duration="2420000" endsAt="1777926658" id="69f3f4fcf84cf881d6b4987a" onAir="0" premiere="0" videoResolution="720" origin="livetv"/></Video><Video guid="plex://episode/69f3f4faf84cf881d6b4980e" key="/library/metadata/69f3f4faf84cf881d6b4980e" ratingKey="69f3f4faf84cf881d6b4980e" summary="Explore Korean crab dishes like Steamed Crab, Grilled Eel, and Parboiled Octopus." type="episode" contentRating="TV-G" duration="3092000" grandparentArt="https://provider-static.plex.tv/epg/cms/production/aef863b1-8d06-4754-a177-3b0c2f19bfde/NEW_KFOOD_Horizontal_Default_Artwork.jpg" grandparentGuid="plex://show/68b9f5a7486bf118339b1c02" grandparentKey="/library/metadata/68b9f5a7486bf118339b1c02" grandparentRatingKey="68b9f5a7486bf118339b1c02" grandparentThumb="https://provider-static.plex.tv/epg/cms/production/62528d3f-fc1e-4168-bbb1-ee9b08230eb5/NEW_KFOOD_Vertical_Default_Artwork.jpg" grandparentTitle="Food Kingdom" grandparentType="show" index="6" originallyAvailableAt="2024-03-04T10:38:05.849Z" parentIndex="0" requiresConsent="1" skipParent="1" thumb="https://ingest-assets.wurl.com/427598/139568321-0.jpeg" title="Food Kingdom : Seafood and Crab Dishes Factory" userState="0" year="2024"><Image alt="Food Kingdom : Seafood and Crab Dishes Factory" type="coverArt" url="https://provider-static.plex.tv/epg/cms/production/aef863b1-8d06-4754-a177-3b0c2f19bfde/NEW_KFOOD_Horizontal_Default_Artwork.jpg"/><Image alt="Food Kingdom : Seafood and Crab Dishes Factory" type="coverPoster" url="https://provider-static.plex.tv/epg/cms/production/62528d3f-fc1e-4168-bbb1-ee9b08230eb5/NEW_KFOOD_Vertical_Default_Artwork.jpg"/><Image alt="Food Kingdom : Seafood and Crab Dishes Factory" type="snapshot" url="https://ingest-assets.wurl.com/427598/139568321-0.jpeg"/><Genre filter="genre=6529021f0f3f142ea6049ecf" id="6529021f0f3f142ea6049ecf" key="/library/sections/home/all?genre=6529021f0f3f142ea6049ecf" ratingKey="genre_6529021f0f3f142ea6049ecf" slug="international" tag="International" type="directory" context="tag.genre"/><Media beginsAt="1777856534" duration="3092000" endsAt="1777859626" id="69f3f4fcf84cf881d6b49866" onAir="0" premiere="0" videoResolution="720" origin="livetv"/></Video><Video guid="plex://episode/69f3f4faf84cf881d6b4980f" key="/library/metadata/69f3f4faf84cf881d6b4980f" ratingKey="69f3f4faf84cf881d6b4980f" summary="Feast on Tteokgalbi, Budae Jjigae, Dry-Aged Meat, and the elegance of the Beef Rib Set." type="episode" contentRating="TV-G" duration="3720000" grandparentArt="https://provider-static.plex.tv/epg/cms/production/aef863b1-8d06-4754-a177-3b0c2f19bfde/NEW_KFOOD_Horizontal_Default_Artwork.jpg" grandparentGuid="plex://show/68b9f5a7486bf118339b1c02" grandparentKey="/library/metadata/68b9f5a7486bf118339b1c02" grandparentRatingKey="68b9f5a7486bf118339b1c02" grandparentThumb="https://provider-static.plex.tv/epg/cms/production/62528d3f-fc1e-4168-bbb1-ee9b08230eb5/NEW_KFOOD_Vertical_Default_Artwork.jpg" grandparentTitle="Food Kingdom" grandparentType="show" index="5" originallyAvailableAt="2024-03-04T10:38:05.849Z" parentIndex="0" requiresConsent="1" skipParent="1" thumb="https://ingest-assets.wurl.com/427598/139568320-0.jpeg" title="Food Kingdom : Meat Product Factory" userState="0" year="2024"><Image alt="Food Kingdom : Meat Product Factory" type="coverArt" url="https://provider-static.plex.tv/epg/cms/production/aef863b1-8d06-4754-a177-3b0c2f19bfde/NEW_KFOOD_Horizontal_Default_Artwork.jpg"/><Image alt="Food Kingdom : Meat Product Factory" type="coverPoster" url="https://provider-static.plex.tv/epg/cms/production/62528d3f-fc1e-4168-bbb1-ee9b08230eb5/NEW_KFOOD_Vertical_Default_Artwork.jpg"/><Image alt="Food Kingdom : Meat Product Factory" type="snapshot" url="https://ingest-assets.wurl.com/427598/139568320-0.jpeg"/><Genre filter="genre=6529021f0f3f142ea6049ecf" id="6529021f0f3f142ea6049ecf" key="/library/sections/home/all?genre=6529021f0f3f142ea6049ecf" ratingKey="genre_6529021f0f3f142ea6049ecf" slug="international" tag="International" type="directory" context="tag.genre"/><Media beginsAt="1777859626" duration="3720000" endsAt="1777863346" id="69f3f4fcf84cf881d6b49867" onAir="0" premiere="0" videoResolution="720" origin="livetv"/></Video><Video guid="plex://episode/69f3f4faf84cf881d6b49810" key="/library/metadata/69f3f4faf84cf881d6b49810" ratingKey="69f3f4faf84cf881d6b49810" summary="Unveil the secrets of crafting Gat Kimchi, Godulbaegi Kimchi, Nurungji, and Lotus Root Chips." type="episode" contentRating="TV-G" duration="3275000" grandparentArt="https://provider-static.plex.tv/epg/cms/production/aef863b1-8d06-4754-a177-3b0c2f19bfde/NEW_KFOOD_Horizontal_Default_Artwork.jpg" grandparentGuid="plex://show/68b9f5a7486bf118339b1c02" grandparentKey="/library/metadata/68b9f5a7486bf118339b1c02" grandparentRatingKey="68b9f5a7486bf118339b1c02" grandparentThumb="https://provider-static.plex.tv/epg/cms/production/62528d3f-fc1e-4168-bbb1-ee9b08230eb5/NEW_KFOOD_Vertical_Default_Artwork.jpg" grandparentTitle="Food Kingdom" grandparentType="show" index="1" originallyAvailableAt="2024-03-04T10:38:05.846Z" parentIndex="0" requiresConsent="1" skipParent="1" thumb="https://ingest-assets.wurl.com/427598/139568316-0.jpeg" title="Food Kingdom : Korean Traditional Food Factory" userState="0" year="2024"><Image alt="Food Kingdom : Korean Traditional Food Factory" type="coverArt" url="https://provider-static.plex.tv/epg/cms/production/aef863b1-8d06-4754-a177-3b0c2f19bfde/NEW_KFOOD_Horizontal_Default_Artwork.jpg"/><Image alt="Food Kingdom : Korean Traditional Food Factory" type="coverPoster" url="https://provider-static.plex.tv/epg/cms/production/62528d3f-fc1e-4168-bbb1-ee9b08230eb5/NEW_KFOOD_Vertical_Default_Artwork.jpg"/><Image alt="Food Kingdom : Korean Traditional Food Factory" type="snapshot" url="https://ingest-assets.wurl.com/427598/139568316-0.jpeg"/><Genre filter="genre=6529021f0f3f142ea6049ecf" id="6529021f0f3f142ea6049ecf" key="/library/sections/home/all?genre=6529021f0f3f142ea6049ecf" ratingKey="genre_6529021f0f3f142ea6049ecf" slug="international" tag="International" type="directory" context="tag.genre"/><Media beginsAt="1777870282" duration="3275000" endsAt="1777873557" id="69f3f4fcf84cf881d6b4986a" onAir="0" premiere="0" videoResolution="720" origin="livetv"/></Video><Video guid="plex://episode/69f3f4faf84cf881d6b49811" key="/library/metadata/69f3f4faf84cf881d6b49811" ratingKey="69f3f4faf84cf881d6b49811" summary="Experience the flavors of Galbitang, Horse Meat Bulgogi, Spicy Braised Beef Feet, and Spicy Kalguksu." type="episode" contentRating="TV-G" duration="3622000" grandparentArt="https://provider-static.plex.tv/epg/cms/production/aef863b1-8d06-4754-a177-3b0c2f19bfde/NEW_KFOOD_Horizontal_Default_Artwork.jpg" grandparentGuid="plex://show/68b9f5a7486bf118339b1c02" grandparentKey="/library/metadata/68b9f5a7486bf118339b1c02" grandparentRatingKey="68b9f5a7486bf118339b1c02" grandparentThumb="https://provider-static.plex.tv/epg/cms/production/62528d3f-fc1e-4168-bbb1-ee9b08230eb5/NEW_KFOOD_Vertical_Default_Artwork.jpg" grandparentTitle="Food Kingdom" grandparentType="show" index="3" originallyAvailableAt="2024-03-04T10:38:05.848Z" parentIndex="0" requiresConsent="1" skipParent="1" thumb="https://ingest-assets.wurl.com/427598/139568318-0.jpeg" title="Food Kingdom : Korean Dishes Factory" userState="0" year="2024"><Image alt="Food Kingdom : Korean Dishes Factory" type="coverArt" url="https://provider-static.plex.tv/epg/cms/production/aef863b1-8d06-4754-a177-3b0c2f19bfde/NEW_KFOOD_Horizontal_Default_Artwork.jpg"/><Image alt="Food Kingdom : Korean Dishes Factory" type="coverPoster" url="https://provider-static.plex.tv/epg/cms/production/62528d3f-fc1e-4168-bbb1-ee9b08230eb5/NEW_KFOOD_Vertical_Default_Artwork.jpg"/><Image alt="Food Kingdom : Korean Dishes Factory" type="snapshot" url="https://ingest-assets.wurl.com/427598/139568318-0.jpeg"/><Genre filter="genre=6529021f0f3f142ea6049ecf" id="6529021f0f3f142ea6049ecf" key="/library/sections/home/all?genre=6529021f0f3f142ea6049ecf" ratingKey="genre_6529021f0f3f142ea6049ecf" slug="international" tag="International" type="directory" context="tag.genre"/><Media beginsAt="1777876780" duration="3622000" endsAt="1777880402" id="69f3f4fcf84cf881d6b4986c" onAir="0" premiere="0" videoResolution="720" origin="livetv"/></Video><Video guid="plex://episode/69f3f4faf84cf881d6b49812" key="/library/metadata/69f3f4faf84cf881d6b49812" ratingKey="69f3f4faf84cf881d6b49812" summary="Feast on tteokbokki, fried snacks, and Korean street food classics in this ultimate snack set episode." type="episode" contentRating="TV-G" duration="3415000" grandparentArt="https://provider-static.plex.tv/epg/cms/production/aef863b1-8d06-4754-a177-3b0c2f19bfde/NEW_KFOOD_Horizontal_Default_Artwork.jpg" grandparentGuid="plex://show/68b9f5a7486bf118339b1c02" grandparentKey="/library/metadata/68b9f5a7486bf118339b1c02" grandparentRatingKey="68b9f5a7486bf118339b1c02" grandparentThumb="https://provider-static.plex.tv/epg/cms/production/62528d3f-fc1e-4168-bbb1-ee9b08230eb5/NEW_KFOOD_Vertical_Default_Artwork.jpg" grandparentTitle="Food Kingdom" grandparentType="show" index="20" originallyAvailableAt="2024-10-16T09:54:15.818Z" parentIndex="1" requiresConsent="1" skipParent="1" thumb="https://ingest-assets.wurl.com/430064/158931718-0.jpeg" title="Food Kingdom: Ultimate Tteokbokki and Snack Set" userState="0" year="2024"><Image alt="Food Kingdom: Ultimate Tteokbokki and Snack Set" type="coverArt" url="https://provider-static.plex.tv/epg/cms/production/aef863b1-8d06-4754-a177-3b0c2f19bfde/NEW_KFOOD_Horizontal_Default_Artwork.jpg"/><Image alt="Food Kingdom: Ultimate Tteokbokki and Snack Set" type="coverPoster" url="https://provider-static.plex.tv/epg/cms/production/62528d3f-fc1e-4168-bbb1-ee9b08230eb5/NEW_KFOOD_Vertical_Default_Artwork.jpg"/><Image alt="Food Kingdom: Ultimate Tteokbokki and Snack Set" type="snapshot" url="https://ingest-assets.wurl.com/430064/158931718-0.jpeg"/><Genre filter="genre=6529021f0f3f142ea6049ecf" id="6529021f0f3f142ea6049ecf" key="/library/sections/home/all?genre=6529021f0f3f142ea6049ecf" ratingKey="genre_6529021f0f3f142ea6049ecf" slug="international" tag="International" type="directory" context="tag.genre"/><Media beginsAt="1777880402" duration="3415000" endsAt="1777883817" id="69f3f4fcf84cf881d6b4986d" onAir="0" premiere="0" videoResolution="720" origin="livetv"/></Video><Video guid="plex://episode/69f3f4faf84cf881d6b49813" key="/library/metadata/69f3f4faf84cf881d6b49813" ratingKey="69f3f4faf84cf881d6b49813" summary="Dive into Korean streets with Cheese Tteokbokki, Mandu, and various street delights." type="episode" contentRating="TV-G" duration="3919000" grandparentArt="https://provider-static.plex.tv/epg/cms/production/aef863b1-8d06-4754-a177-3b0c2f19bfde/NEW_KFOOD_Horizontal_Default_Artwork.jpg" grandparentGuid="plex://show/68b9f5a7486bf118339b1c02" grandparentKey="/library/metadata/68b9f5a7486bf118339b1c02" grandparentRatingKey="68b9f5a7486bf118339b1c02" grandparentThumb="https://provider-static.plex.tv/epg/cms/production/62528d3f-fc1e-4168-bbb1-ee9b08230eb5/NEW_KFOOD_Vertical_Default_Artwork.jpg" grandparentTitle="Food Kingdom" grandparentType="show" index="12" originallyAvailableAt="2024-03-04T10:38:05.851Z" parentIndex="0" requiresConsent="1" skipParent="1" thumb="https://ingest-assets.wurl.com/427598/139568327-0.jpeg" title="Food Kingdom : Korean Street Food" userState="0" year="2024"><Image alt="Food Kingdom : Korean Street Food" type="coverArt" url="https://provider-static.plex.tv/epg/cms/production/aef863b1-8d06-4754-a177-3b0c2f19bfde/NEW_KFOOD_Horizontal_Default_Artwork.jpg"/><Image alt="Food Kingdom : Korean Street Food" type="coverPoster" url="https://provider-static.plex.tv/epg/cms/production/62528d3f-fc1e-4168-bbb1-ee9b08230eb5/NEW_KFOOD_Vertical_Default_Artwork.jpg"/><Image alt="Food Kingdom : Korean Street Food" type="snapshot" url="https://ingest-assets.wurl.com/427598/139568327-0.jpeg"/><Genre filter="genre=6529021f0f3f142ea6049ecf" id="6529021f0f3f142ea6049ecf" key="/library/sections/home/all?genre=6529021f0f3f142ea6049ecf" ratingKey="genre_6529021f0f3f142ea6049ecf" slug="international" tag="International" type="directory" context="tag.genre"/><Media beginsAt="1777893986" duration="3919000" endsAt="1777897905" id="69f3f4fcf84cf881d6b49871" onAir="0" premiere="0" videoResolution="720" origin="livetv"/></Video><Video guid="plex://episode/69f3f4faf84cf881d6b49814" key="/library/metadata/69f3f4faf84cf881d6b49814" ratingKey="69f3f4faf84cf881d6b49814" summary="Explore Korean agriculture with Mushroom, Cherry Tomato, Vegetable, Dairy Cow, and Egg Farms." type="episode" contentRating="TV-G" duration="4202000" grandparentArt="https://provider-static.plex.tv/epg/cms/production/aef863b1-8d06-4754-a177-3b0c2f19bfde/NEW_KFOOD_Horizontal_Default_Artwork.jpg" grandparentGuid="plex://show/68b9f5a7486bf118339b1c02" grandparentKey="/library/metadata/68b9f5a7486bf118339b1c02" grandparentRatingKey="68b9f5a7486bf118339b1c02" grandparentThumb="https://provider-static.plex.tv/epg/cms/production/62528d3f-fc1e-4168-bbb1-ee9b08230eb5/NEW_KFOOD_Vertical_Default_Artwork.jpg" grandparentTitle="Food Kingdom" grandparentType="show" index="7" originallyAvailableAt="2024-03-04T10:38:05.850Z" parentIndex="0" requiresConsent="1" skipParent="1" thumb="https://ingest-assets.wurl.com/427598/139568322-0.jpeg" title="Food Kingdom : Korean Farm" userState="0" year="2024"><Image alt="Food Kingdom : Korean Farm" type="coverArt" url="https://provider-static.plex.tv/epg/cms/production/aef863b1-8d06-4754-a177-3b0c2f19bfde/NEW_KFOOD_Horizontal_Default_Artwork.jpg"/><Image alt="Food Kingdom : Korean Farm" type="coverPoster" url="https://provider-static.plex.tv/epg/cms/production/62528d3f-fc1e-4168-bbb1-ee9b08230eb5/NEW_KFOOD_Vertical_Default_Artwork.jpg"/><Image alt="Food Kingdom : Korean Farm" type="snapshot" url="https://ingest-assets.wurl.com/427598/139568322-0.jpeg"/><Genre filter="genre=6529021f0f3f142ea6049ecf" id="6529021f0f3f142ea6049ecf" key="/library/sections/home/all?genre=6529021f0f3f142ea6049ecf" ratingKey="genre_6529021f0f3f142ea6049ecf" slug="international" tag="International" type="directory" context="tag.genre"/><Media beginsAt="1777897905" duration="4202000" endsAt="1777902107" id="69f3f4fcf84cf881d6b49872" onAir="0" premiere="0" videoResolution="720" origin="livetv"/></Video><Video guid="plex://episode/69f3f4fbf84cf881d6b49815" key="/library/metadata/69f3f4fbf84cf881d6b49815" ratingKey="69f3f4fbf84cf881d6b49815" summary="Savor grilled pork belly, abalone butter fried rice, and Jeju black pork for a hearty Korean pork feast." type="episode" contentRating="TV-G" duration="2887000" grandparentArt="https://provider-static.plex.tv/epg/cms/production/aef863b1-8d06-4754-a177-3b0c2f19bfde/NEW_KFOOD_Horizontal_Default_Artwork.jpg" grandparentGuid="plex://show/68b9f5a7486bf118339b1c02" grandparentKey="/library/metadata/68b9f5a7486bf118339b1c02" grandparentRatingKey="68b9f5a7486bf118339b1c02" grandparentThumb="https://provider-static.plex.tv/epg/cms/production/62528d3f-fc1e-4168-bbb1-ee9b08230eb5/NEW_KFOOD_Vertical_Default_Artwork.jpg" grandparentTitle="Food Kingdom" grandparentType="show" index="22" originallyAvailableAt="2024-11-05T04:42:57.438Z" parentIndex="1" requiresConsent="1" skipParent="1" thumb="https://ingest-assets.wurl.com/430279/160802906-0.jpeg" title="Food Kingdom: Grilled Pork Specials" userState="0" year="2024"><Image alt="Food Kingdom: Grilled Pork Specials" type="coverArt" url="https://provider-static.plex.tv/epg/cms/production/aef863b1-8d06-4754-a177-3b0c2f19bfde/NEW_KFOOD_Horizontal_Default_Artwork.jpg"/><Image alt="Food Kingdom: Grilled Pork Specials" type="coverPoster" url="https://provider-static.plex.tv/epg/cms/production/62528d3f-fc1e-4168-bbb1-ee9b08230eb5/NEW_KFOOD_Vertical_Default_Artwork.jpg"/><Image alt="Food Kingdom: Grilled Pork Specials" type="snapshot" url="https://ingest-assets.wurl.com/430279/160802906-0.jpeg"/><Genre filter="genre=6529021f0f3f142ea6049ecf" id="6529021f0f3f142ea6049ecf" key="/library/sections/home/all?genre=6529021f0f3f142ea6049ecf" ratingKey="genre_6529021f0f3f142ea6049ecf" slug="international" tag="International" type="directory" context="tag.genre"/><Media beginsAt="1777911518" duration="2887000" endsAt="1777914405" id="69f3f4fcf84cf881d6b49876" onAir="0" premiere="0" videoResolution="720" origin="livetv"/></Video><Video guid="plex://episode/69f3f4fbf84cf881d6b49816" key="/library/metadata/69f3f4fbf84cf881d6b49816" ratingKey="69f3f4fbf84cf881d6b49816" summary="Explore diversity with Texas Charcoal Smoked Barbeque, a Korean pub&apos;s menu, and molecular gastronomy delights." type="episode" contentRating="TV-G" duration="3448000" grandparentArt="https://provider-static.plex.tv/epg/cms/production/aef863b1-8d06-4754-a177-3b0c2f19bfde/NEW_KFOOD_Horizontal_Default_Artwork.jpg" grandparentGuid="plex://show/68b9f5a7486bf118339b1c02" grandparentKey="/library/metadata/68b9f5a7486bf118339b1c02" grandparentRatingKey="68b9f5a7486bf118339b1c02" grandparentThumb="https://provider-static.plex.tv/epg/cms/production/62528d3f-fc1e-4168-bbb1-ee9b08230eb5/NEW_KFOOD_Vertical_Default_Artwork.jpg" grandparentTitle="Food Kingdom" grandparentType="show" index="13" originallyAvailableAt="2024-03-04T10:38:05.852Z" parentIndex="0" requiresConsent="1" skipParent="1" thumb="https://ingest-assets.wurl.com/427598/139568328-0.jpeg" title="Food Kingdom : Various Dishes" userState="0" year="2024"><Image alt="Food Kingdom : Various Dishes" type="coverArt" url="https://provider-static.plex.tv/epg/cms/production/aef863b1-8d06-4754-a177-3b0c2f19bfde/NEW_KFOOD_Horizontal_Default_Artwork.jpg"/><Image alt="Food Kingdom : Various Dishes" type="coverPoster" url="https://provider-static.plex.tv/epg/cms/production/62528d3f-fc1e-4168-bbb1-ee9b08230eb5/NEW_KFOOD_Vertical_Default_Artwork.jpg"/><Image alt="Food Kingdom : Various Dishes" type="snapshot" url="https://ingest-assets.wurl.com/427598/139568328-0.jpeg"/><Genre filter="genre=6529021f0f3f142ea6049ecf" id="6529021f0f3f142ea6049ecf" key="/library/sections/home/all?genre=6529021f0f3f142ea6049ecf" ratingKey="genre_6529021f0f3f142ea6049ecf" slug="international" tag="International" type="directory" context="tag.genre"/><Media beginsAt="1777914405" duration="3448000" endsAt="1777917853" id="69f3f4fcf84cf881d6b49877" onAir="0" premiere="0" videoResolution="720" origin="livetv"/></Video><Video guid="plex://episode/69f3f4fbf84cf881d6b49817" key="/library/metadata/69f3f4fbf84cf881d6b49817" ratingKey="69f3f4fbf84cf881d6b49817" summary="Enjoy the blend of Tempura Rice Bowl, Japanese dishes, Soft Tofu Jjambbong, and beloved Chinese classics." type="episode" contentRating="TV-G" duration="4255000" grandparentArt="https://provider-static.plex.tv/epg/cms/production/aef863b1-8d06-4754-a177-3b0c2f19bfde/NEW_KFOOD_Horizontal_Default_Artwork.jpg" grandparentGuid="plex://show/68b9f5a7486bf118339b1c02" grandparentKey="/library/metadata/68b9f5a7486bf118339b1c02" grandparentRatingKey="68b9f5a7486bf118339b1c02" grandparentThumb="https://provider-static.plex.tv/epg/cms/production/62528d3f-fc1e-4168-bbb1-ee9b08230eb5/NEW_KFOOD_Vertical_Default_Artwork.jpg" grandparentTitle="Food Kingdom" grandparentType="show" index="11" originallyAvailableAt="2024-03-04T10:38:05.851Z" parentIndex="0" requiresConsent="1" skipParent="1" thumb="https://ingest-assets.wurl.com/427598/139568326-0.jpeg" title="Food Kingdom : East Asian Fusion" userState="0" year="2024"><Image alt="Food Kingdom : East Asian Fusion" type="coverArt" url="https://provider-static.plex.tv/epg/cms/production/aef863b1-8d06-4754-a177-3b0c2f19bfde/NEW_KFOOD_Horizontal_Default_Artwork.jpg"/><Image alt="Food Kingdom : East Asian Fusion" type="coverPoster" url="https://provider-static.plex.tv/epg/cms/production/62528d3f-fc1e-4168-bbb1-ee9b08230eb5/NEW_KFOOD_Vertical_Default_Artwork.jpg"/><Image alt="Food Kingdom : East Asian Fusion" type="snapshot" url="https://ingest-assets.wurl.com/427598/139568326-0.jpeg"/><Genre filter="genre=6529021f0f3f142ea6049ecf" id="6529021f0f3f142ea6049ecf" key="/library/sections/home/all?genre=6529021f0f3f142ea6049ecf" ratingKey="genre_6529021f0f3f142ea6049ecf" slug="international" tag="International" type="directory" context="tag.genre"/><Media beginsAt="1777936449" duration="4255000" endsAt="1777940704" id="69f3f4fcf84cf881d6b4987e" onAir="0" premiere="0" videoResolution="720" origin="livetv"/></Video></MediaContainer>
</tv>