<tv channelGridKey="63894c1965b848bf2c8a7800">
<MediaContainer offset="0" totalSize="15" identifier="tv.plex.provider.epg" size="15"><Video art="https://provider-static.plex.tv/epg/cms/production/4a134b06-1d11-4ff9-834e-35e2a4fb5050/5-Minute_Crafts_Horizontalrdx.jpg" guid="plex://movie/63894c1a32a481754a5751f5" key="/library/metadata/63894c1a32a481754a5751f5" ratingKey="63894c1a32a481754a5751f5" summary="5-Minute Crafts is the most-watched DIY digital brand in the world, known for its positive, entertaining, and quirky DIY crafts." type="movie" duration="3600000" requiresConsent="1" skipParent="1" thumb="https://provider-static.plex.tv/epg/cms/production/1701ac92-64d5-439c-9ec3-51c2727ceed9/5-Minute_Crafts_1000x1500_1VERT.jpg" title="5-Minute Crafts" userState="0"><Image alt="5-Minute Crafts" type="coverArt" url="https://provider-static.plex.tv/epg/cms/production/4a134b06-1d11-4ff9-834e-35e2a4fb5050/5-Minute_Crafts_Horizontalrdx.jpg"/><Image alt="5-Minute Crafts" type="coverPoster" url="https://provider-static.plex.tv/epg/cms/production/1701ac92-64d5-439c-9ec3-51c2727ceed9/5-Minute_Crafts_1000x1500_1VERT.jpg"/><Genre filter="genre=6668f7413bfb7848eb53639d" id="6668f7413bfb7848eb53639d" key="/library/sections/home/all?genre=6668f7413bfb7848eb53639d" ratingKey="genre_6668f7413bfb7848eb53639d" slug="food-home" tag="Food + Home" type="directory" context="tag.genre"/><Media beginsAt="1776924519" duration="3600000" endsAt="1776928119" id="69e8173584fa3578a1c9bb49" onAir="0" premiere="0" videoResolution="720" origin="livetv"/><Media beginsAt="1776928119" duration="3600000" endsAt="1776931719" id="69e8173584fa3578a1c9bb4a" onAir="0" premiere="0" videoResolution="720" origin="livetv"/><Media beginsAt="1776931719" duration="3600000" endsAt="1776935319" id="69e8173584fa3578a1c9bb4b" onAir="0" premiere="0" videoResolution="720" origin="livetv"/><Media beginsAt="1776935319" duration="3600000" endsAt="1776938919" id="69e8173584fa3578a1c9bb4c" onAir="0" premiere="0" videoResolution="720" origin="livetv"/><Media beginsAt="1776938919" duration="3600000" endsAt="1776942519" id="69e8173584fa3578a1c9bb4d" onAir="0" premiere="0" videoResolution="720" origin="livetv"/><Media beginsAt="1776942519" duration="3600000" endsAt="1776946119" id="69e8173584fa3578a1c9bb4e" onAir="0" premiere="0" videoResolution="720" origin="livetv"/><Media beginsAt="1776946119" duration="3600000" endsAt="1776949719" id="69e8173584fa3578a1c9bb4f" onAir="0" premiere="0" videoResolution="720" origin="livetv"/><Media beginsAt="1776949719" duration="3600000" endsAt="1776953319" id="69e8173584fa3578a1c9bb50" onAir="0" premiere="0" videoResolution="720" origin="livetv"/><Media beginsAt="1776953319" duration="3600000" endsAt="1776956919" id="69e8173584fa3578a1c9bb51" onAir="0" premiere="0" videoResolution="720" origin="livetv"/><Media beginsAt="1776956919" duration="3600000" endsAt="1776960519" id="69e8173584fa3578a1c9bb52" onAir="0" premiere="0" videoResolution="720" origin="livetv"/><Media beginsAt="1776960519" duration="3600000" endsAt="1776964119" id="69e8173584fa3578a1c9bb53" onAir="0" premiere="0" videoResolution="720" origin="livetv"/><Media beginsAt="1776964119" duration="3600000" endsAt="1776967719" id="69e8173584fa3578a1c9bb54" onAir="0" premiere="0" videoResolution="720" origin="livetv"/><Media beginsAt="1776967719" duration="3600000" endsAt="1776971319" id="69e8173584fa3578a1c9bb55" onAir="0" premiere="0" videoResolution="720" origin="livetv"/><Media beginsAt="1776971319" duration="3600000" endsAt="1776974919" id="69e8173584fa3578a1c9bb56" onAir="0" premiere="0" videoResolution="720" origin="livetv"/><Media beginsAt="1776974919" duration="3600000" endsAt="1776978519" id="69e8173584fa3578a1c9bb57" onAir="0" premiere="0" videoResolution="720" origin="livetv"/><Media beginsAt="1776978519" duration="3600000" endsAt="1776982119" id="69e8173584fa3578a1c9bb58" onAir="0" premiere="0" videoResolution="720" origin="livetv"/><Media beginsAt="1776982119" duration="3600000" endsAt="1776985719" id="69e8173584fa3578a1c9bb59" onAir="0" premiere="0" videoResolution="720" origin="livetv"/><Media beginsAt="1776985719" duration="3600000" endsAt="1776989319" id="69e8173584fa3578a1c9bb5a" onAir="0" premiere="0" videoResolution="720" origin="livetv"/></Video><Video guid="plex://episode/69e8172f84fa3578a1c9baf1" key="/library/metadata/69e8172f84fa3578a1c9baf1" ratingKey="69e8172f84fa3578a1c9baf1" summary="In this video, we share some expert-level tips and tricks to help all gardeners out there take their hobby to the next level." type="episode" contentRating="L" duration="3072000" grandparentArt="https://provider-static.plex.tv/epg/cms/production/4a134b06-1d11-4ff9-834e-35e2a4fb5050/5-Minute_Crafts_Horizontalrdx.jpg" grandparentGuid="plex://show/69e8172f84fa3578a1c9baf0" grandparentKey="/library/metadata/69e8172f84fa3578a1c9baf0" grandparentRatingKey="69e8172f84fa3578a1c9baf0" grandparentThumb="https://provider-static.plex.tv/epg/cms/production/1701ac92-64d5-439c-9ec3-51c2727ceed9/5-Minute_Crafts_1000x1500_1VERT.jpg" grandparentTitle="Top Life Hacks Every Gardener Should Know" grandparentType="show" index="341" originallyAvailableAt="2022-10-31T00:00:00Z" parentIndex="1" requiresConsent="1" skipParent="1" thumb="https://provider-static.plex.tv/epg/cms/production/4a134b06-1d11-4ff9-834e-35e2a4fb5050/5-Minute_Crafts_Horizontalrdx.jpg" title="5-Minute Crafts" userState="0" year="2022"><Image alt="5-Minute Crafts" type="coverArt" url="https://provider-static.plex.tv/epg/cms/production/4a134b06-1d11-4ff9-834e-35e2a4fb5050/5-Minute_Crafts_Horizontalrdx.jpg"/><Image alt="5-Minute Crafts" type="coverPoster" url="https://provider-static.plex.tv/epg/cms/production/1701ac92-64d5-439c-9ec3-51c2727ceed9/5-Minute_Crafts_1000x1500_1VERT.jpg"/><Image alt="5-Minute Crafts" type="snapshot" url="https://provider-static.plex.tv/epg/cms/production/4a134b06-1d11-4ff9-834e-35e2a4fb5050/5-Minute_Crafts_Horizontalrdx.jpg"/><Genre filter="genre=6668f7413bfb7848eb53639d" id="6668f7413bfb7848eb53639d" key="/library/sections/home/all?genre=6668f7413bfb7848eb53639d" ratingKey="genre_6668f7413bfb7848eb53639d" slug="food-home" tag="Food + Home" type="directory" context="tag.genre"/><Media beginsAt="1776900403" duration="3603000" endsAt="1776904006" id="69e8173584fa3578a1c9bb3b" onAir="1" premiere="0" videoResolution="720" origin="livetv"/></Video><Video guid="plex://episode/69e8173084fa3578a1c9baf9" key="/library/metadata/69e8173084fa3578a1c9baf9" ratingKey="69e8173084fa3578a1c9baf9" summary="In this video, we share some of the ultimate camping hacks that will make your outdoor adventure more enjoyable and hassle-free. From setting up camp to cooking meals, we&apos;ve got you covered with insider tips and tricks that will make you a pro at camping." type="episode" contentRating="L" duration="2812000" grandparentArt="https://provider-static.plex.tv/epg/cms/production/4a134b06-1d11-4ff9-834e-35e2a4fb5050/5-Minute_Crafts_Horizontalrdx.jpg" grandparentGuid="plex://show/69e8173084fa3578a1c9baf8" grandparentKey="/library/metadata/69e8173084fa3578a1c9baf8" grandparentRatingKey="69e8173084fa3578a1c9baf8" grandparentThumb="https://provider-static.plex.tv/epg/cms/production/1701ac92-64d5-439c-9ec3-51c2727ceed9/5-Minute_Crafts_1000x1500_1VERT.jpg" grandparentTitle="Ultimate Camping Hacks for a Hassle-Free Adventure" grandparentType="show" index="345" originallyAvailableAt="2022-10-31T00:00:00Z" parentIndex="1" requiresConsent="1" skipParent="1" thumb="https://provider-static.plex.tv/epg/cms/production/4a134b06-1d11-4ff9-834e-35e2a4fb5050/5-Minute_Crafts_Horizontalrdx.jpg" title="5-Minute Crafts" userState="0" year="2022"><Image alt="5-Minute Crafts" type="coverArt" url="https://provider-static.plex.tv/epg/cms/production/4a134b06-1d11-4ff9-834e-35e2a4fb5050/5-Minute_Crafts_Horizontalrdx.jpg"/><Image alt="5-Minute Crafts" type="coverPoster" url="https://provider-static.plex.tv/epg/cms/production/1701ac92-64d5-439c-9ec3-51c2727ceed9/5-Minute_Crafts_1000x1500_1VERT.jpg"/><Image alt="5-Minute Crafts" type="snapshot" url="https://provider-static.plex.tv/epg/cms/production/4a134b06-1d11-4ff9-834e-35e2a4fb5050/5-Minute_Crafts_Horizontalrdx.jpg"/><Genre filter="genre=6668f7413bfb7848eb53639d" id="6668f7413bfb7848eb53639d" key="/library/sections/home/all?genre=6668f7413bfb7848eb53639d" ratingKey="genre_6668f7413bfb7848eb53639d" slug="food-home" tag="Food + Home" type="directory" context="tag.genre"/><Media beginsAt="1776904006" duration="3068000" endsAt="1776907074" id="69e8173584fa3578a1c9bb3c" onAir="0" premiere="0" videoResolution="720" origin="livetv"/></Video><Video guid="plex://episode/69e8173084fa3578a1c9bafd" key="/library/metadata/69e8173084fa3578a1c9bafd" ratingKey="69e8173084fa3578a1c9bafd" summary="In this video, we will showcase handy repair hacks that can help you save time and money." type="episode" contentRating="L" duration="1473000" grandparentArt="https://provider-static.plex.tv/epg/cms/production/4a134b06-1d11-4ff9-834e-35e2a4fb5050/5-Minute_Crafts_Horizontalrdx.jpg" grandparentGuid="plex://show/69e8173084fa3578a1c9bafc" grandparentKey="/library/metadata/69e8173084fa3578a1c9bafc" grandparentRatingKey="69e8173084fa3578a1c9bafc" grandparentThumb="https://provider-static.plex.tv/epg/cms/production/1701ac92-64d5-439c-9ec3-51c2727ceed9/5-Minute_Crafts_1000x1500_1VERT.jpg" grandparentTitle="Useful Repair Hacks That Will Save You Time and Money" grandparentType="show" index="361" originallyAvailableAt="2022-10-31T00:00:00Z" parentIndex="1" requiresConsent="1" skipParent="1" thumb="https://provider-static.plex.tv/epg/cms/production/4a134b06-1d11-4ff9-834e-35e2a4fb5050/5-Minute_Crafts_Horizontalrdx.jpg" title="5-Minute Crafts" userState="0" year="2022"><Image alt="5-Minute Crafts" type="coverArt" url="https://provider-static.plex.tv/epg/cms/production/4a134b06-1d11-4ff9-834e-35e2a4fb5050/5-Minute_Crafts_Horizontalrdx.jpg"/><Image alt="5-Minute Crafts" type="coverPoster" url="https://provider-static.plex.tv/epg/cms/production/1701ac92-64d5-439c-9ec3-51c2727ceed9/5-Minute_Crafts_1000x1500_1VERT.jpg"/><Image alt="5-Minute Crafts" type="snapshot" url="https://provider-static.plex.tv/epg/cms/production/4a134b06-1d11-4ff9-834e-35e2a4fb5050/5-Minute_Crafts_Horizontalrdx.jpg"/><Genre filter="genre=6668f7413bfb7848eb53639d" id="6668f7413bfb7848eb53639d" key="/library/sections/home/all?genre=6668f7413bfb7848eb53639d" ratingKey="genre_6668f7413bfb7848eb53639d" slug="food-home" tag="Food + Home" type="directory" context="tag.genre"/><Media beginsAt="1776907074" duration="1474000" endsAt="1776908548" id="69e8173584fa3578a1c9bb3d" onAir="0" premiere="0" videoResolution="720" origin="livetv"/></Video><Video guid="plex://episode/69e8173084fa3578a1c9baff" key="/library/metadata/69e8173084fa3578a1c9baff" ratingKey="69e8173084fa3578a1c9baff" summary="In this video, we explore the world of smart car hacks that can change your experience completely." type="episode" contentRating="L" duration="1454000" grandparentArt="https://provider-static.plex.tv/epg/cms/production/4a134b06-1d11-4ff9-834e-35e2a4fb5050/5-Minute_Crafts_Horizontalrdx.jpg" grandparentGuid="plex://show/69e8173084fa3578a1c9bafe" grandparentKey="/library/metadata/69e8173084fa3578a1c9bafe" grandparentRatingKey="69e8173084fa3578a1c9bafe" grandparentThumb="https://provider-static.plex.tv/epg/cms/production/1701ac92-64d5-439c-9ec3-51c2727ceed9/5-Minute_Crafts_1000x1500_1VERT.jpg" grandparentTitle="The Ultimate Guide To Smart Car Hacks" grandparentType="show" index="364" originallyAvailableAt="2022-10-31T00:00:00Z" parentIndex="1" requiresConsent="1" skipParent="1" thumb="https://provider-static.plex.tv/epg/cms/production/4a134b06-1d11-4ff9-834e-35e2a4fb5050/5-Minute_Crafts_Horizontalrdx.jpg" title="5-Minute Crafts" userState="0" year="2022"><Image alt="5-Minute Crafts" type="coverArt" url="https://provider-static.plex.tv/epg/cms/production/4a134b06-1d11-4ff9-834e-35e2a4fb5050/5-Minute_Crafts_Horizontalrdx.jpg"/><Image alt="5-Minute Crafts" type="coverPoster" url="https://provider-static.plex.tv/epg/cms/production/1701ac92-64d5-439c-9ec3-51c2727ceed9/5-Minute_Crafts_1000x1500_1VERT.jpg"/><Image alt="5-Minute Crafts" type="snapshot" url="https://provider-static.plex.tv/epg/cms/production/4a134b06-1d11-4ff9-834e-35e2a4fb5050/5-Minute_Crafts_Horizontalrdx.jpg"/><Genre filter="genre=6668f7413bfb7848eb53639d" id="6668f7413bfb7848eb53639d" key="/library/sections/home/all?genre=6668f7413bfb7848eb53639d" ratingKey="genre_6668f7413bfb7848eb53639d" slug="food-home" tag="Food + Home" type="directory" context="tag.genre"/><Media beginsAt="1776908548" duration="1333000" endsAt="1776909881" id="69e8173584fa3578a1c9bb3e" onAir="0" premiere="0" videoResolution="720" origin="livetv"/></Video><Video guid="plex://episode/69e8173184fa3578a1c9bb01" key="/library/metadata/69e8173184fa3578a1c9bb01" ratingKey="69e8173184fa3578a1c9bb01" summary="In this video, we will share with you the top camping hacks that every camper should know!" type="episode" contentRating="L" duration="1548000" grandparentArt="https://provider-static.plex.tv/epg/cms/production/4a134b06-1d11-4ff9-834e-35e2a4fb5050/5-Minute_Crafts_Horizontalrdx.jpg" grandparentGuid="plex://show/69e8173184fa3578a1c9bb00" grandparentKey="/library/metadata/69e8173184fa3578a1c9bb00" grandparentRatingKey="69e8173184fa3578a1c9bb00" grandparentThumb="https://provider-static.plex.tv/epg/cms/production/1701ac92-64d5-439c-9ec3-51c2727ceed9/5-Minute_Crafts_1000x1500_1VERT.jpg" grandparentTitle="Camp Like A Pro With These Top Camping Hacks!" grandparentType="show" index="360" originallyAvailableAt="2022-10-31T00:00:00Z" parentIndex="1" requiresConsent="1" skipParent="1" thumb="https://provider-static.plex.tv/epg/cms/production/4a134b06-1d11-4ff9-834e-35e2a4fb5050/5-Minute_Crafts_Horizontalrdx.jpg" title="5-Minute Crafts" userState="0" year="2022"><Image alt="5-Minute Crafts" type="coverArt" url="https://provider-static.plex.tv/epg/cms/production/4a134b06-1d11-4ff9-834e-35e2a4fb5050/5-Minute_Crafts_Horizontalrdx.jpg"/><Image alt="5-Minute Crafts" type="coverPoster" url="https://provider-static.plex.tv/epg/cms/production/1701ac92-64d5-439c-9ec3-51c2727ceed9/5-Minute_Crafts_1000x1500_1VERT.jpg"/><Image alt="5-Minute Crafts" type="snapshot" url="https://provider-static.plex.tv/epg/cms/production/4a134b06-1d11-4ff9-834e-35e2a4fb5050/5-Minute_Crafts_Horizontalrdx.jpg"/><Genre filter="genre=6668f7413bfb7848eb53639d" id="6668f7413bfb7848eb53639d" key="/library/sections/home/all?genre=6668f7413bfb7848eb53639d" ratingKey="genre_6668f7413bfb7848eb53639d" slug="food-home" tag="Food + Home" type="directory" context="tag.genre"/><Media beginsAt="1776909881" duration="1669000" endsAt="1776911550" id="69e8173584fa3578a1c9bb3f" onAir="0" premiere="0" videoResolution="720" origin="livetv"/></Video><Video guid="plex://episode/69e8173184fa3578a1c9bb03" key="/library/metadata/69e8173184fa3578a1c9bb03" ratingKey="69e8173184fa3578a1c9bb03" summary="Watch as we take a bland and uninspired room and turn it into something truly extraordinary in this epic room transformation video!" type="episode" contentRating="L" duration="1802000" grandparentArt="https://provider-static.plex.tv/epg/cms/production/4a134b06-1d11-4ff9-834e-35e2a4fb5050/5-Minute_Crafts_Horizontalrdx.jpg" grandparentGuid="plex://show/69e8173184fa3578a1c9bb02" grandparentKey="/library/metadata/69e8173184fa3578a1c9bb02" grandparentRatingKey="69e8173184fa3578a1c9bb02" grandparentThumb="https://provider-static.plex.tv/epg/cms/production/1701ac92-64d5-439c-9ec3-51c2727ceed9/5-Minute_Crafts_1000x1500_1VERT.jpg" grandparentTitle="Epic Room Transformation: Before and After" grandparentType="show" index="349" originallyAvailableAt="2022-10-31T00:00:00Z" parentIndex="1" requiresConsent="1" skipParent="1" thumb="https://provider-static.plex.tv/epg/cms/production/4a134b06-1d11-4ff9-834e-35e2a4fb5050/5-Minute_Crafts_Horizontalrdx.jpg" title="5-Minute Crafts" userState="0" year="2022"><Image alt="5-Minute Crafts" type="coverArt" url="https://provider-static.plex.tv/epg/cms/production/4a134b06-1d11-4ff9-834e-35e2a4fb5050/5-Minute_Crafts_Horizontalrdx.jpg"/><Image alt="5-Minute Crafts" type="coverPoster" url="https://provider-static.plex.tv/epg/cms/production/1701ac92-64d5-439c-9ec3-51c2727ceed9/5-Minute_Crafts_1000x1500_1VERT.jpg"/><Image alt="5-Minute Crafts" type="snapshot" url="https://provider-static.plex.tv/epg/cms/production/4a134b06-1d11-4ff9-834e-35e2a4fb5050/5-Minute_Crafts_Horizontalrdx.jpg"/><Genre filter="genre=6668f7413bfb7848eb53639d" id="6668f7413bfb7848eb53639d" key="/library/sections/home/all?genre=6668f7413bfb7848eb53639d" ratingKey="genre_6668f7413bfb7848eb53639d" slug="food-home" tag="Food + Home" type="directory" context="tag.genre"/><Media beginsAt="1776911550" duration="1801000" endsAt="1776913351" id="69e8173584fa3578a1c9bb40" onAir="0" premiere="0" videoResolution="720" origin="livetv"/></Video><Video guid="plex://episode/69e8173184fa3578a1c9bb05" key="/library/metadata/69e8173184fa3578a1c9bb05" ratingKey="69e8173184fa3578a1c9bb05" summary="Looking for some clever solutions to everyday problems that will make your life easier?" type="episode" contentRating="L" duration="1824000" grandparentArt="https://provider-static.plex.tv/epg/cms/production/4a134b06-1d11-4ff9-834e-35e2a4fb5050/5-Minute_Crafts_Horizontalrdx.jpg" grandparentGuid="plex://show/69e8173184fa3578a1c9bb04" grandparentKey="/library/metadata/69e8173184fa3578a1c9bb04" grandparentRatingKey="69e8173184fa3578a1c9bb04" grandparentThumb="https://provider-static.plex.tv/epg/cms/production/1701ac92-64d5-439c-9ec3-51c2727ceed9/5-Minute_Crafts_1000x1500_1VERT.jpg" grandparentTitle="Random and Surprisingly Useful Tips You Need to Know" grandparentType="show" index="362" originallyAvailableAt="2022-10-31T00:00:00Z" parentIndex="1" requiresConsent="1" skipParent="1" thumb="https://provider-static.plex.tv/epg/cms/production/4a134b06-1d11-4ff9-834e-35e2a4fb5050/5-Minute_Crafts_Horizontalrdx.jpg" title="5-Minute Crafts" userState="0" year="2022"><Image alt="5-Minute Crafts" type="coverArt" url="https://provider-static.plex.tv/epg/cms/production/4a134b06-1d11-4ff9-834e-35e2a4fb5050/5-Minute_Crafts_Horizontalrdx.jpg"/><Image alt="5-Minute Crafts" type="coverPoster" url="https://provider-static.plex.tv/epg/cms/production/1701ac92-64d5-439c-9ec3-51c2727ceed9/5-Minute_Crafts_1000x1500_1VERT.jpg"/><Image alt="5-Minute Crafts" type="snapshot" url="https://provider-static.plex.tv/epg/cms/production/4a134b06-1d11-4ff9-834e-35e2a4fb5050/5-Minute_Crafts_Horizontalrdx.jpg"/><Genre filter="genre=6668f7413bfb7848eb53639d" id="6668f7413bfb7848eb53639d" key="/library/sections/home/all?genre=6668f7413bfb7848eb53639d" ratingKey="genre_6668f7413bfb7848eb53639d" slug="food-home" tag="Food + Home" type="directory" context="tag.genre"/><Media beginsAt="1776913351" duration="1824000" endsAt="1776915175" id="69e8173584fa3578a1c9bb41" onAir="0" premiere="0" videoResolution="720" origin="livetv"/></Video><Video guid="plex://episode/69e8173184fa3578a1c9bb07" key="/library/metadata/69e8173184fa3578a1c9bb07" ratingKey="69e8173184fa3578a1c9bb07" summary="Melting and pouring metal for cool crafts!" type="episode" contentRating="L" duration="1225000" grandparentArt="https://provider-static.plex.tv/epg/cms/production/4a134b06-1d11-4ff9-834e-35e2a4fb5050/5-Minute_Crafts_Horizontalrdx.jpg" grandparentGuid="plex://show/69e8173184fa3578a1c9bb06" grandparentKey="/library/metadata/69e8173184fa3578a1c9bb06" grandparentRatingKey="69e8173184fa3578a1c9bb06" grandparentThumb="https://provider-static.plex.tv/epg/cms/production/1701ac92-64d5-439c-9ec3-51c2727ceed9/5-Minute_Crafts_1000x1500_1VERT.jpg" grandparentTitle="Pouring And Melting Metal Hacks" grandparentType="show" index="355" originallyAvailableAt="2022-10-31T00:00:00Z" parentIndex="1" requiresConsent="1" skipParent="1" thumb="https://provider-static.plex.tv/epg/cms/production/4a134b06-1d11-4ff9-834e-35e2a4fb5050/5-Minute_Crafts_Horizontalrdx.jpg" title="5-Minute Crafts" userState="0" year="2022"><Image alt="5-Minute Crafts" type="coverArt" url="https://provider-static.plex.tv/epg/cms/production/4a134b06-1d11-4ff9-834e-35e2a4fb5050/5-Minute_Crafts_Horizontalrdx.jpg"/><Image alt="5-Minute Crafts" type="coverPoster" url="https://provider-static.plex.tv/epg/cms/production/1701ac92-64d5-439c-9ec3-51c2727ceed9/5-Minute_Crafts_1000x1500_1VERT.jpg"/><Image alt="5-Minute Crafts" type="snapshot" url="https://provider-static.plex.tv/epg/cms/production/4a134b06-1d11-4ff9-834e-35e2a4fb5050/5-Minute_Crafts_Horizontalrdx.jpg"/><Genre filter="genre=6668f7413bfb7848eb53639d" id="6668f7413bfb7848eb53639d" key="/library/sections/home/all?genre=6668f7413bfb7848eb53639d" ratingKey="genre_6668f7413bfb7848eb53639d" slug="food-home" tag="Food + Home" type="directory" context="tag.genre"/><Media beginsAt="1776915175" duration="1225000" endsAt="1776916400" id="69e8173584fa3578a1c9bb42" onAir="0" premiere="0" videoResolution="720" origin="livetv"/></Video><Video guid="plex://episode/69e8173284fa3578a1c9bb09" key="/library/metadata/69e8173284fa3578a1c9bb09" ratingKey="69e8173284fa3578a1c9bb09" summary="This video is a must-watch for all parents out there struggling to keep up with the demands of parenthood." type="episode" contentRating="L" duration="2660000" grandparentArt="https://provider-static.plex.tv/epg/cms/production/4a134b06-1d11-4ff9-834e-35e2a4fb5050/5-Minute_Crafts_Horizontalrdx.jpg" grandparentGuid="plex://show/69e8173184fa3578a1c9bb08" grandparentKey="/library/metadata/69e8173184fa3578a1c9bb08" grandparentRatingKey="69e8173184fa3578a1c9bb08" grandparentThumb="https://provider-static.plex.tv/epg/cms/production/1701ac92-64d5-439c-9ec3-51c2727ceed9/5-Minute_Crafts_1000x1500_1VERT.jpg" grandparentTitle="Genius Parenting Hacks You Need To Know!" grandparentType="show" index="340" originallyAvailableAt="2022-10-31T00:00:00Z" parentIndex="1" requiresConsent="1" skipParent="1" thumb="https://provider-static.plex.tv/epg/cms/production/4a134b06-1d11-4ff9-834e-35e2a4fb5050/5-Minute_Crafts_Horizontalrdx.jpg" title="5-Minute Crafts" userState="0" year="2022"><Image alt="5-Minute Crafts" type="coverArt" url="https://provider-static.plex.tv/epg/cms/production/4a134b06-1d11-4ff9-834e-35e2a4fb5050/5-Minute_Crafts_Horizontalrdx.jpg"/><Image alt="5-Minute Crafts" type="coverPoster" url="https://provider-static.plex.tv/epg/cms/production/1701ac92-64d5-439c-9ec3-51c2727ceed9/5-Minute_Crafts_1000x1500_1VERT.jpg"/><Image alt="5-Minute Crafts" type="snapshot" url="https://provider-static.plex.tv/epg/cms/production/4a134b06-1d11-4ff9-834e-35e2a4fb5050/5-Minute_Crafts_Horizontalrdx.jpg"/><Genre filter="genre=6668f7413bfb7848eb53639d" id="6668f7413bfb7848eb53639d" key="/library/sections/home/all?genre=6668f7413bfb7848eb53639d" ratingKey="genre_6668f7413bfb7848eb53639d" slug="food-home" tag="Food + Home" type="directory" context="tag.genre"/><Media beginsAt="1776916400" duration="2541000" endsAt="1776918941" id="69e8173584fa3578a1c9bb43" onAir="0" premiere="0" videoResolution="720" origin="livetv"/></Video><Video guid="plex://episode/69e8173284fa3578a1c9bb0b" key="/library/metadata/69e8173284fa3578a1c9bb0b" ratingKey="69e8173284fa3578a1c9bb0b" summary="This video demonstrates amazing repair hacks for fixing common household problems that anyone can do like a pro." type="episode" contentRating="L" duration="245000" grandparentArt="https://provider-static.plex.tv/epg/cms/production/4a134b06-1d11-4ff9-834e-35e2a4fb5050/5-Minute_Crafts_Horizontalrdx.jpg" grandparentGuid="plex://show/69e8173284fa3578a1c9bb0a" grandparentKey="/library/metadata/69e8173284fa3578a1c9bb0a" grandparentRatingKey="69e8173284fa3578a1c9bb0a" grandparentThumb="https://provider-static.plex.tv/epg/cms/production/1701ac92-64d5-439c-9ec3-51c2727ceed9/5-Minute_Crafts_1000x1500_1VERT.jpg" grandparentTitle="Repair Hacks to Fix Common Household Problems Like a Pro" grandparentType="show" index="342" originallyAvailableAt="2022-10-31T00:00:00Z" parentIndex="1" requiresConsent="1" skipParent="1" thumb="https://provider-static.plex.tv/epg/cms/production/4a134b06-1d11-4ff9-834e-35e2a4fb5050/5-Minute_Crafts_Horizontalrdx.jpg" title="5-Minute Crafts" userState="0" year="2022"><Image alt="5-Minute Crafts" type="coverArt" url="https://provider-static.plex.tv/epg/cms/production/4a134b06-1d11-4ff9-834e-35e2a4fb5050/5-Minute_Crafts_Horizontalrdx.jpg"/><Image alt="5-Minute Crafts" type="coverPoster" url="https://provider-static.plex.tv/epg/cms/production/1701ac92-64d5-439c-9ec3-51c2727ceed9/5-Minute_Crafts_1000x1500_1VERT.jpg"/><Image alt="5-Minute Crafts" type="snapshot" url="https://provider-static.plex.tv/epg/cms/production/4a134b06-1d11-4ff9-834e-35e2a4fb5050/5-Minute_Crafts_Horizontalrdx.jpg"/><Genre filter="genre=6668f7413bfb7848eb53639d" id="6668f7413bfb7848eb53639d" key="/library/sections/home/all?genre=6668f7413bfb7848eb53639d" ratingKey="genre_6668f7413bfb7848eb53639d" slug="food-home" tag="Food + Home" type="directory" context="tag.genre"/><Media beginsAt="1776918941" duration="364000" endsAt="1776919305" id="69e8173584fa3578a1c9bb44" onAir="0" premiere="0" videoResolution="720" origin="livetv"/></Video><Video guid="plex://episode/69e8173284fa3578a1c9bb0d" key="/library/metadata/69e8173284fa3578a1c9bb0d" ratingKey="69e8173284fa3578a1c9bb0d" summary="This video features a collection of easy and delicious recipes that are perfect for busy people." type="episode" contentRating="L" duration="2797000" grandparentArt="https://provider-static.plex.tv/epg/cms/production/4a134b06-1d11-4ff9-834e-35e2a4fb5050/5-Minute_Crafts_Horizontalrdx.jpg" grandparentGuid="plex://show/69e8173284fa3578a1c9bb0c" grandparentKey="/library/metadata/69e8173284fa3578a1c9bb0c" grandparentRatingKey="69e8173284fa3578a1c9bb0c" grandparentThumb="https://provider-static.plex.tv/epg/cms/production/1701ac92-64d5-439c-9ec3-51c2727ceed9/5-Minute_Crafts_1000x1500_1VERT.jpg" grandparentTitle="Quick And Tasty: Simple Recipes For Busy People" grandparentType="show" index="337" originallyAvailableAt="2022-10-31T00:00:00Z" parentIndex="1" requiresConsent="1" skipParent="1" thumb="https://provider-static.plex.tv/epg/cms/production/4a134b06-1d11-4ff9-834e-35e2a4fb5050/5-Minute_Crafts_Horizontalrdx.jpg" title="5-Minute Crafts" userState="0" year="2022"><Image alt="5-Minute Crafts" type="coverArt" url="https://provider-static.plex.tv/epg/cms/production/4a134b06-1d11-4ff9-834e-35e2a4fb5050/5-Minute_Crafts_Horizontalrdx.jpg"/><Image alt="5-Minute Crafts" type="coverPoster" url="https://provider-static.plex.tv/epg/cms/production/1701ac92-64d5-439c-9ec3-51c2727ceed9/5-Minute_Crafts_1000x1500_1VERT.jpg"/><Image alt="5-Minute Crafts" type="snapshot" url="https://provider-static.plex.tv/epg/cms/production/4a134b06-1d11-4ff9-834e-35e2a4fb5050/5-Minute_Crafts_Horizontalrdx.jpg"/><Genre filter="genre=6668f7413bfb7848eb53639d" id="6668f7413bfb7848eb53639d" key="/library/sections/home/all?genre=6668f7413bfb7848eb53639d" ratingKey="genre_6668f7413bfb7848eb53639d" slug="food-home" tag="Food + Home" type="directory" context="tag.genre"/><Media beginsAt="1776919305" duration="2677000" endsAt="1776921982" id="69e8173584fa3578a1c9bb45" onAir="0" premiere="0" videoResolution="720" origin="livetv"/></Video><Video guid="plex://episode/69e8173384fa3578a1c9bb0f" key="/library/metadata/69e8173384fa3578a1c9bb0f" ratingKey="69e8173384fa3578a1c9bb0f" summary="Learn how to make mealtime easier and more delicious with our top cooking hacks and recipes in this informative video." type="episode" contentRating="L" duration="1500000" grandparentArt="https://provider-static.plex.tv/epg/cms/production/4a134b06-1d11-4ff9-834e-35e2a4fb5050/5-Minute_Crafts_Horizontalrdx.jpg" grandparentGuid="plex://show/69e8173384fa3578a1c9bb0e" grandparentKey="/library/metadata/69e8173384fa3578a1c9bb0e" grandparentRatingKey="69e8173384fa3578a1c9bb0e" grandparentThumb="https://provider-static.plex.tv/epg/cms/production/1701ac92-64d5-439c-9ec3-51c2727ceed9/5-Minute_Crafts_1000x1500_1VERT.jpg" grandparentTitle="Time-Saving Cooking Hacks and Delicious Recipes" grandparentType="show" index="352" originallyAvailableAt="2022-10-31T00:00:00Z" parentIndex="1" requiresConsent="1" skipParent="1" thumb="https://provider-static.plex.tv/epg/cms/production/4a134b06-1d11-4ff9-834e-35e2a4fb5050/5-Minute_Crafts_Horizontalrdx.jpg" title="5-Minute Crafts" userState="0" year="2022"><Image alt="5-Minute Crafts" type="coverArt" url="https://provider-static.plex.tv/epg/cms/production/4a134b06-1d11-4ff9-834e-35e2a4fb5050/5-Minute_Crafts_Horizontalrdx.jpg"/><Image alt="5-Minute Crafts" type="coverPoster" url="https://provider-static.plex.tv/epg/cms/production/1701ac92-64d5-439c-9ec3-51c2727ceed9/5-Minute_Crafts_1000x1500_1VERT.jpg"/><Image alt="5-Minute Crafts" type="snapshot" url="https://provider-static.plex.tv/epg/cms/production/4a134b06-1d11-4ff9-834e-35e2a4fb5050/5-Minute_Crafts_Horizontalrdx.jpg"/><Genre filter="genre=6668f7413bfb7848eb53639d" id="6668f7413bfb7848eb53639d" key="/library/sections/home/all?genre=6668f7413bfb7848eb53639d" ratingKey="genre_6668f7413bfb7848eb53639d" slug="food-home" tag="Food + Home" type="directory" context="tag.genre"/><Media beginsAt="1776921982" duration="1500000" endsAt="1776923482" id="69e8173584fa3578a1c9bb46" onAir="0" premiere="0" videoResolution="720" origin="livetv"/></Video><Video guid="plex://episode/69e8173384fa3578a1c9bb11" key="/library/metadata/69e8173384fa3578a1c9bb11" ratingKey="69e8173384fa3578a1c9bb11" summary="In this informative and practical video, you will discover the top repair hacks that can save you time and money." type="episode" contentRating="L" duration="264000" grandparentArt="https://provider-static.plex.tv/epg/cms/production/4a134b06-1d11-4ff9-834e-35e2a4fb5050/5-Minute_Crafts_Horizontalrdx.jpg" grandparentGuid="plex://show/69e8173384fa3578a1c9bb10" grandparentKey="/library/metadata/69e8173384fa3578a1c9bb10" grandparentRatingKey="69e8173384fa3578a1c9bb10" grandparentThumb="https://provider-static.plex.tv/epg/cms/production/1701ac92-64d5-439c-9ec3-51c2727ceed9/5-Minute_Crafts_1000x1500_1VERT.jpg" grandparentTitle="Top Repair Hacks You Need to Know" grandparentType="show" index="353" originallyAvailableAt="2022-10-31T00:00:00Z" parentIndex="1" requiresConsent="1" skipParent="1" thumb="https://provider-static.plex.tv/epg/cms/production/4a134b06-1d11-4ff9-834e-35e2a4fb5050/5-Minute_Crafts_Horizontalrdx.jpg" title="5-Minute Crafts" userState="0" year="2022"><Image alt="5-Minute Crafts" type="coverArt" url="https://provider-static.plex.tv/epg/cms/production/4a134b06-1d11-4ff9-834e-35e2a4fb5050/5-Minute_Crafts_Horizontalrdx.jpg"/><Image alt="5-Minute Crafts" type="coverPoster" url="https://provider-static.plex.tv/epg/cms/production/1701ac92-64d5-439c-9ec3-51c2727ceed9/5-Minute_Crafts_1000x1500_1VERT.jpg"/><Image alt="5-Minute Crafts" type="snapshot" url="https://provider-static.plex.tv/epg/cms/production/4a134b06-1d11-4ff9-834e-35e2a4fb5050/5-Minute_Crafts_Horizontalrdx.jpg"/><Genre filter="genre=6668f7413bfb7848eb53639d" id="6668f7413bfb7848eb53639d" key="/library/sections/home/all?genre=6668f7413bfb7848eb53639d" ratingKey="genre_6668f7413bfb7848eb53639d" slug="food-home" tag="Food + Home" type="directory" context="tag.genre"/><Media beginsAt="1776923482" duration="265000" endsAt="1776923747" id="69e8173584fa3578a1c9bb47" onAir="0" premiere="0" videoResolution="720" origin="livetv"/></Video><Video guid="plex://episode/69e8173384fa3578a1c9bb13" key="/library/metadata/69e8173384fa3578a1c9bb13" ratingKey="69e8173384fa3578a1c9bb13" summary="Learn how to make your furry friend&apos;s life better with these easy hacks and pet-friendly crafts in our latest video tutorial." type="episode" contentRating="L" duration="1268000" grandparentArt="https://provider-static.plex.tv/epg/cms/production/4a134b06-1d11-4ff9-834e-35e2a4fb5050/5-Minute_Crafts_Horizontalrdx.jpg" grandparentGuid="plex://show/69e8173384fa3578a1c9bb12" grandparentKey="/library/metadata/69e8173384fa3578a1c9bb12" grandparentRatingKey="69e8173384fa3578a1c9bb12" grandparentThumb="https://provider-static.plex.tv/epg/cms/production/1701ac92-64d5-439c-9ec3-51c2727ceed9/5-Minute_Crafts_1000x1500_1VERT.jpg" grandparentTitle="DIY Hacks and Crafts for Your Furry Friends" grandparentType="show" index="351" originallyAvailableAt="2022-10-31T00:00:00Z" parentIndex="1" requiresConsent="1" skipParent="1" thumb="https://provider-static.plex.tv/epg/cms/production/4a134b06-1d11-4ff9-834e-35e2a4fb5050/5-Minute_Crafts_Horizontalrdx.jpg" title="5-Minute Crafts" userState="0" year="2022"><Image alt="5-Minute Crafts" type="coverArt" url="https://provider-static.plex.tv/epg/cms/production/4a134b06-1d11-4ff9-834e-35e2a4fb5050/5-Minute_Crafts_Horizontalrdx.jpg"/><Image alt="5-Minute Crafts" type="coverPoster" url="https://provider-static.plex.tv/epg/cms/production/1701ac92-64d5-439c-9ec3-51c2727ceed9/5-Minute_Crafts_1000x1500_1VERT.jpg"/><Image alt="5-Minute Crafts" type="snapshot" url="https://provider-static.plex.tv/epg/cms/production/4a134b06-1d11-4ff9-834e-35e2a4fb5050/5-Minute_Crafts_Horizontalrdx.jpg"/><Genre filter="genre=6668f7413bfb7848eb53639d" id="6668f7413bfb7848eb53639d" key="/library/sections/home/all?genre=6668f7413bfb7848eb53639d" ratingKey="genre_6668f7413bfb7848eb53639d" slug="food-home" tag="Food + Home" type="directory" context="tag.genre"/><Media beginsAt="1776923747" duration="772000" endsAt="1776924519" id="69e8173584fa3578a1c9bb48" onAir="0" premiere="0" videoResolution="720" origin="livetv"/></Video></MediaContainer>
</tv>